{
  "document": {
    "id": "efta00017896",
    "filename": "EFTA00017896.pdf",
    "path": "C:\\Users\\user\\CascadeProjects\\epsteinexposed\\apps\\web\\DataSet 8\\VOL00008\\IMAGES\\0003\\EFTA00017896.pdf",
    "text": "\n\nEvent: Epstein/Maxwell FOIA \nStart Date: 2021-03-10 22:00:00 +0000 \nEnd Date: 2021-03-10 22:30:00 +0000 \nOrganizer: (USANYS) < \nClass: X-PERSONAL \nDate Created: 2021-03-10 20:40:03 +0000 \nDate Modified: 2021-03-10 20:40:03 +0000 \nPriority: 5 \nDTSTAMP: 2021-03-10 20:13:35 +0000 \nAttendee: \nAlarm: Display the following message 15m before start \nReminder \n-- Do not delete or change any of the following text. --\nWhen it's time, join your Webex meeting here. \nJoin meeting \nMore ways to join: \n> \nJoin from the meeting link \nEFTA00017896\n\nhttps://usao.webex.com/usao/j.php?MTID=mc1bb5eedOecOce74c174ac88e8ccbd53 \nJoin by meeting number \nMeeting number (access code): 199 962 1511 \nMeeting password: PMxMsPua532 \nTap to join from a mobile device (attendees only) \n,1999621511## USA Toll 2 \n,1999621511## US Toll \nJoin by phone \nUSA Toll 2 \nUS Toll \nGlobal call-in numbers \nJoin from a video system or application \nDial 1999621511@usao.webex.com \nYou can also dial 207.182.190.20 and enter your meeting number. \nJoin using Microsoft Lync or Microsoft Skype for Business \nDial 1999621511.usao@lync.webex.com \nIf you are a host, click here to view host information. \nNeed help? Go to https://help.webex.com \nEFTA00017897",
    "pageCount": 2,
    "dataset": "Dataset 8"
  },
  "entities": {
    "people": [
      {
        "name": "Start Date",
        "role": "extracted",
        "context": "Event: Epstein/Maxwell FOIA \nStart Date: 2021-03-10 22:00:00 +0000 \nE"
      },
      {
        "name": "End Date",
        "role": "extracted",
        "context": "e: 2021-03-10 22:00:00 +0000 \nEnd Date: 2021-03-10 22:30:00 +0000 \nO"
      },
      {
        "name": "Date Created",
        "role": "extracted",
        "context": "USANYS) < \nClass: X-PERSONAL \nDate Created: 2021-03-10 20:40:03 +0000 \nD"
      },
      {
        "name": "Date Modified",
        "role": "extracted",
        "context": "d: 2021-03-10 20:40:03 +0000 \nDate Modified: 2021-03-10 20:40:03 +0000 \nP"
      },
      {
        "name": "Toll \nJoin",
        "role": "extracted",
        "context": "USA Toll 2 \n,1999621511## US Toll \nJoin by phone \nUSA Toll 2 \nUS Toll"
      },
      {
        "name": "Toll \nGlobal",
        "role": "extracted",
        "context": "Join by phone \nUSA Toll 2 \nUS Toll \nGlobal call-in numbers \nJoin from a"
      },
      {
        "name": "Microsoft Lync",
        "role": "extracted",
        "context": "r meeting number. \nJoin using Microsoft Lync or Microsoft Skype for Busine"
      },
      {
        "name": "Microsoft Skype",
        "role": "extracted",
        "context": "Join using Microsoft Lync or Microsoft Skype for Business \nDial 1999621511"
      },
      {
        "name": "Business \nDial",
        "role": "extracted",
        "context": "t Lync or Microsoft Skype for Business \nDial 1999621511.usao@lync.webex.co"
      }
    ],
    "locations": [],
    "dates": [
      {
        "date": "2021-03-10",
        "event": "2021-03-10"
      }
    ],
    "flights": [],
    "phone_numbers": [
      "199 962 1511"
    ],
    "organizations": []
  },
  "processedAt": "2025-12-23T12:25:55.816Z"
}