{
  "document": {
    "id": "efta00026849",
    "filename": "EFTA00026849.pdf",
    "path": "C:\\Users\\user\\CascadeProjects\\epsteinexposed\\apps\\web\\DataSet 8\\VOL00008\\IMAGES\\0005\\EFTA00026849.pdf",
    "text": "\n\nFrom: ' \nTo: \nJeffJocks <jjocks®sondeeracine.com> \nCc: '\nnlElllyt t \nSubject: RE: Subpoena to Interlochen Center for the Arts \nDate: Wed, 12 Feb 2020 21:10:12 +0000 \nAttachments: 2020-02-10,NDO_&_subpoena_to_Interlochenflor student_recordsL.docx.pdf \nJeff, \nAs discussed, attached please find a second subpoena with an accompanying non-disclosure order. Please feel free to \ngive me a call with any questions. \nThanks, \nMaurene \nAssistant United States Attorney \nSouthern District of New York \n1  St. Andrew's Plaza \nNew York, NY 10007 \n212-637-2324 \nFrom: Jeff Jocks <jjocks@sondeeracine.com> \nSent: Thursday, February 6, 2020 2:46 PM \nTo: \nCc: \nSubject: Re: Subpoena to Interlochen Center for the Arts \nMaurene — \nReceipt confirmed. \nThanks, \nJeff \nJeffrey L. Jocks \nSondee, Racine & Doren, PLC \n310 West Front Street, Suite 300 \nTraverse City, Michigan 49684 \n231-947-0400 \njjocksPsondeeracine.com \nwww.sondeeracine.com \nCONFIDENTIALITY NOTICE: The information contained in this email and any attachments is intended for the use of the \naddressee only. Its contents may be privileged, confidential, and exempt from disclosure under applicable law. If you are \nnot the named addressee, please delete it immediately. Thank you. \nEFTA00026849\n\nFrom: '\nDate: Thursday, February 6, 2020 at 1:51 PM \nTo: Jeff Jocks <jjocks@sondeeracine.com>\nCc:' \nH \nSubject: Subpoena to Interlochen Center for the Arts \nJeff, \nAs discussed, attached please find a subpoena addressed to Interlochen seeking information regarding Jeffrey Epstein and \nGhislaine Maxwell. Per our conversation, we understand that Interlochen will keep this request confidential. \nPlease let me know if you have any questions or would like to discuss further. \nBest, \nMaurene \nAssistant United States Attorney \nSouthern District of New York \n1 St. Andrew's Plaza \nNew York, NY 10007 \n212-637-2324 \nEFTA00026850",
    "pageCount": 2,
    "dataset": "Dataset 8"
  },
  "entities": {
    "people": [
      {
        "name": "Jeffrey Epstein",
        "role": "extracted",
        "context": "ssed to Interlochen seeking information regarding Jeffrey Epstein and \nGhislaine Maxwell. Per our conversation, we"
      },
      {
        "name": "Ghislaine Maxwell",
        "role": "extracted",
        "context": "eeking information regarding Jeffrey Epstein and \nGhislaine Maxwell. Per our conversation, we understand that Interlo"
      },
      {
        "name": "Interlochen Center",
        "role": "extracted",
        "context": "t t \nSubject: RE: Subpoena to Interlochen Center for the Arts \nDate: Wed, 12 F"
      },
      {
        "name": "Arts \nDate",
        "role": "extracted",
        "context": "to Interlochen Center for the Arts \nDate: Wed, 12 Feb 2020 21:10:12 +0"
      },
      {
        "name": "Maurene \nAssistant",
        "role": "extracted",
        "context": "with any questions. \nThanks, \nMaurene \nAssistant United States Attorney \nSouth"
      },
      {
        "name": "Attorney \nSouthern",
        "role": "extracted",
        "context": "rene \nAssistant United States Attorney \nSouthern District of New York \n1  St."
      },
      {
        "name": "Plaza \nNew",
        "role": "extracted",
        "context": "of New York \n1  St. Andrew's Plaza \nNew York, NY 10007 \n212-637-2324"
      },
      {
        "name": "Jeff Jocks",
        "role": "extracted",
        "context": "NY 10007 \n212-637-2324 \nFrom: Jeff Jocks <jjocks@sondeeracine.com> \nSe"
      },
      {
        "name": "Arts \nMaurene",
        "role": "extracted",
        "context": "to Interlochen Center for the Arts \nMaurene — \nReceipt confirmed. \nThanks"
      },
      {
        "name": "Jeff \nJeffrey",
        "role": "extracted",
        "context": "Receipt confirmed. \nThanks, \nJeff \nJeffrey L. Jocks \nSondee, Racine & Do"
      },
      {
        "name": "Jocks \nSondee",
        "role": "extracted",
        "context": "d. \nThanks, \nJeff \nJeffrey L. Jocks \nSondee, Racine & Doren, PLC \n310 Wes"
      },
      {
        "name": "West Front",
        "role": "extracted",
        "context": "dee, Racine & Doren, PLC \n310 West Front Street, Suite 300 \nTraverse C"
      },
      {
        "name": "Traverse City",
        "role": "extracted",
        "context": "West Front Street, Suite 300 \nTraverse City, Michigan 49684 \n231-947-0400"
      },
      {
        "name": "Arts \nJeff",
        "role": "extracted",
        "context": "to Interlochen Center for the Arts \nJeff, \nAs discussed, attached plea"
      }
    ],
    "locations": [
      {
        "name": "New York, NY",
        "type": "city"
      }
    ],
    "dates": [
      {
        "date": "2020-02-10",
        "event": "2020-02-10"
      },
      {
        "date": "2020-02-06",
        "event": "February 6, 2020"
      }
    ],
    "flights": [],
    "phone_numbers": [
      "212-637-2324",
      "231-947-0400"
    ],
    "organizations": []
  },
  "processedAt": "2025-12-23T12:26:16.971Z"
}