{
  "document": {
    "id": "efta00023918",
    "filename": "EFTA00023918.pdf",
    "path": "C:\\Users\\user\\CascadeProjects\\epsteinexposed\\apps\\web\\DataSet 8\\VOL00008\\IMAGES\\0005\\EFTA00023918.pdf",
    "text": "\n\nFrom: \" \nSubject: FW: US v. Maxwell, 52 20 Cr. 330 (AJN) \nDate: Wed, 16 Jun 2021 03:44:27 +0000 \nAttachments: Maxwell_Reply_to_6-7-21_Conditions_Ltr.pdf \nPlease see the attached letter from Maxwell's counsel. Do you have time this week for a  call to discuss, please? \nThanks, \nAssistant United States Attorney \nSouthern District of New York \n1 St. Andrew's Plaza \nFrom: BOBBI C STERNHEIM <bcsternheim@mac.com> \nSent: Tuesday, June 15, 2021 6:49 PM \nTo: \nCc: Christian Everdell <CEverdell@CohenGresser.com>; Laura Menninger <Imenninger@hmflaw.com>; Jeff Pagliuca \n<jpagliuca@hmflaw.com> \nSubject: US v. Maxwell, 52 20 Cr. 330 (AJN) \nGood evening-\nAttached is a courtesy copy of today's ECF fling. \nRegards, \nBobbi \nBOBBI C. STERNHEIM, ESQ. \nLaw Offices of Bobbi C. Sternheim \n33 West 19th Street - 4th Floor \nNew York, NY 10011 \nMain: 212-243-1100 \nCell: 917-912-9698 \nFax: 888-587-4737 \nbcsternheim@mac.com \n• •Covid-19 Notice: The West 19th Street office is currently closed but we continue to work remotely. \nEFTA00023918\n\nPlease use email or fax, instead of regular mail, for all correspondence during this time. \nWe continue to work regular business hours throughout this situation. \nThank you for your consideration. Our best wishes for your good health and well being. \nThis message and any attached documents contain information from the Law Offices of Bobbi C. Sternheim \nthat may be confidential and/or privileged. \nIf you are not the intended recipient, you may not read, copy, distribute, or use this information. \nIf you have received this transmission in error, please notify the sender immediately by reply e-mail and then delete this \nmessage. Thank you. \nOn Jun 7, 2021, at 9:42 PM, wrote: \nGood evening, \nAttached please find the Government's letter updating the Court about the defendant's conditions of confinement at \nthe MDC. The Government is still waiting to hear from defense counsel whether they are seeking redactions. \nAccordingly, the Government is submitting the letter by email to the Court temporarily under seal to give the defense an \nopportunity to propose and justify any redactions it deems necessary. We will file the letter on the docket at the Court's \ndirection. \nRespectfully submitted, \nAssistant United States Attorney \nUnited States Attorney's Office \nSouthern District of New York \n<2021-06-07 GM letter update re MDC conditions final.pdf> \nEFTA00023919",
    "pageCount": 2,
    "dataset": "Dataset 8"
  },
  "entities": {
    "people": [
      {
        "name": "Assistant United",
        "role": "extracted",
        "context": "to discuss, please? \nThanks, \nAssistant United States Attorney \nSouthern Dis"
      },
      {
        "name": "States Attorney",
        "role": "extracted",
        "context": "e? \nThanks, \nAssistant United States Attorney \nSouthern District of New Yor"
      },
      {
        "name": "Southern District",
        "role": "extracted",
        "context": "stant United States Attorney \nSouthern District of New York \n1 St. Andrew's P"
      },
      {
        "name": "Plaza \nFrom",
        "role": "extracted",
        "context": "t of New York \n1 St. Andrew's Plaza \nFrom: BOBBI C STERNHEIM <bcsternhe"
      },
      {
        "name": "Christian Everdell",
        "role": "extracted",
        "context": "ne 15, 2021 6:49 PM \nTo: \nCc: Christian Everdell <CEverdell@CohenGresser.com>;"
      },
      {
        "name": "Laura Menninger",
        "role": "extracted",
        "context": "<CEverdell@CohenGresser.com>; Laura Menninger <Imenninger@hmflaw.com>; Jeff"
      },
      {
        "name": "Jeff Pagliuca",
        "role": "extracted",
        "context": "nger <Imenninger@hmflaw.com>; Jeff Pagliuca \n<jpagliuca@hmflaw.com> \nSubj"
      },
      {
        "name": "Law Offices",
        "role": "extracted",
        "context": "bi \nBOBBI C. STERNHEIM, ESQ. \nLaw Offices of Bobbi C. Sternheim \n33 Wes"
      },
      {
        "name": "Floor \nNew",
        "role": "extracted",
        "context": "im \n33 West 19th Street - 4th Floor \nNew York, NY 10011 \nMain: 212-243"
      },
      {
        "name": "The West",
        "role": "extracted",
        "context": "@mac.com \n• •Covid-19 Notice: The West 19th Street office is current"
      },
      {
        "name": "On Jun",
        "role": "extracted",
        "context": "te this \nmessage. Thank you. \nOn Jun 7, 2021, at 9:42 PM, wrote:"
      },
      {
        "name": "The Government",
        "role": "extracted",
        "context": "s of confinement at \nthe MDC. The Government is still waiting to hear from"
      },
      {
        "name": "Office \nSouthern",
        "role": "extracted",
        "context": "ney \nUnited States Attorney's Office \nSouthern District of New York \n<2021-0"
      }
    ],
    "locations": [
      {
        "name": "New York, NY",
        "type": "city"
      }
    ],
    "dates": [
      {
        "date": "2021-06-07",
        "event": "2021-06-07"
      },
      {
        "date": "2021-06-15",
        "event": "June 15, 2021"
      }
    ],
    "flights": [],
    "phone_numbers": [
      "212-243-1100",
      "917-912-9698",
      "888-587-4737"
    ],
    "organizations": []
  },
  "processedAt": "2025-12-23T12:26:09.881Z"
}