{
  "document": {
    "id": "efta00019207",
    "filename": "EFTA00019207.pdf",
    "path": "C:\\Users\\user\\CascadeProjects\\epsteinexposed\\apps\\web\\DataSet 8\\VOL00008\\IMAGES\\0003\\EFTA00019207.pdf",
    "text": "\n\nFrom: \nTo: \n )1.\nSubject: RE: Your Amazon.com order of \"2019 Newest HP Pavilion 15...\" and 2 more items. \nDate: The, 10 Nov 2020 20:28:23 +0000 \nAttachments: 2020-11-10,_GM, _letter to_MDC_Warden.docx \nI just addressed it to — if this looks okay to you, once. reviews it we can email the letter to \nhow she'd like us to get the laptop to MDC. \nFrom: \nSent: Tuesday, November 10, 2020 2:26 PM \nTo: \nSubject: RE: Your Amazon.com order of \"2019 Newest HP Pavilion 15...\" and 2 more items. \nand ask her \nI don't know the new Warden's name. I think it's fine to just address it to \"Warden, Metropolitan Correctional Center\". \nThanks! \nFrom \nSent: Tuesday, November 10, 202012:26 PM \nTo) \nSubject: Fwd: Your Amazon.com order of \"2019 Newest HP Pavilion 15...\" and 2 more items. \nWhat is the warden's name? I can draft the letter we discussed. \nSent from my iPhone \nBegin forwarded message: \nFrom: (USANYS)\"  \nDate: November 10, 2020 at 12:23:28 PM EST \nTo: ' \nCc: \nUSANYS)\" \n)11\n(USANYS)\" \nSubject: RE: Your Amazon.com order of \"2019 Newest HP Pavilion and 2 more items. \nThe Maxwell Laptop is ready to be picked up in room 307. We removed all the laptops electronic communication, so it \nhas no Wi-Fi, Bluetooth or Ethernet connection capabilities. We tested access to the production data with the backup \nBOP production and works fine. We placed a sticker on the laptop with the password. \nLet me know if you have any questions. \nFrom: \nSent: Monday, November 9, 2020 8:53 PM \nTo: -(USANYS) \nCc: III (USANYS) (USANYS) \nSubject: RE: Your    mazon.com order of \"2019 Newest HP Pavilion 15...\" and 2 more items. \nThanks so much, Is the laptop large enough to save any of Maxwell's discovery on it? Or would doing so just slow \nit down? I ask because her attorneys requested that we load her discovery onto the laptop if possible. \nEFTA00019207\n\nFrom: (USANYS) \nSent: Monday, November 9, 2020 2:11 PM \nTo \nCc: (USANYS) \n(USANYS) < \nSubject: RE: Your Amazon.com order of \"2019 Newest HP Pavilion 15...\" and 2 more items. \nIt will be ready tomorrow morning. \nFrom: IMME) \nSent: Monday, November 9, 2020 2:09 PM \nTo: USANYS).> \nCc: (USAN\n \n)1 \nUSANYS) \nu ect: Re: Your Amazon.com order of \"2019 Newest HP Pavilion 15...\" and 2 more items. \nHi MR \nJust checking on this— do you have an estimate of timing? \nThanks very much, \nSent from my iPhone \nOn Nov 6, 2020, at 11:00 AM, (USANYS' wrote: \nHard to tell it depends on getting all the updates loaded and configured. Let you know later when we have more info. \nFrom \nSent: F \nTo: \nCc: \nday, November 6, 2020 10:57 AM \n(USANYS) \nUSANYS) \n(USANYS) \nSubject: Re: Your Amazon.com order of \"2019 Newest HP Pavilion 15...\" and 2 more items. \nThanks very much, do you think it will be possible for us to deliver this to MDC on Monday? \nSent from my iPhone \nOn \nNov 6, 2020, at 10:41 AM, (USANYS) wrote: \nIt has we are currently testing and configuring it to ensure it meets BOP standards. \nFrom: \nSent: Friday, November 6, 2020 10:33 AM \na; \nTo USANYS) \nCc: USANYS \n(USANYS) \nSubject: RE: Your Amazon.com order of \"2019 Newest HP Pavilion 15...\" and 2 more items. \nEFTA00019208\n\nHi \nThanks again for your help with this —  I'm checking in on the status of the laptop. Has it arrived? \nThanks, \nFrom: (USANYS) \nSent: Tuesday, November 3, 2020 7:20 AM \nTo \nUSANYS) \nSubject: FW: Your Amazon.com order of \"2019 Newest HP Pavilion 15...\" and 2 more items. \nSee below.... looks like the laptop might be here by Friday but most likely early next week. See below. \nFrom: \n(USANYS) < \nSent: Monday, November 2, 2020 3:09 PM \nTo: (USANYS) \nCc: I (USANYS) < \n); \n(USANYS) \nSubject: FW: Your Amazon.com order of \"2019 Newest HP Pavilion 15...\" and 2 more items. \nFYI \nFrom: Amazon.com \n<auto-confirm@amazon.com> \nSent: Monday, November 02 2020 3:08 PM \nTo:MISUSANYS) \nSubject: Your Amazon.com order of \"2019 Newest HP Pavilion 15...\" and 2 more items. \nL4.-\nAmazon.c\nam \nYour \nAccount \nAmazon.com \nOrder Confirmation \nOrder \n#111-2544752-6074601 \nOrder #111-0303935-3604241 \nOrder #111-3128522-0349002 \nHello-\nThank you for shopping with us. We'll send a confirmation once your items have shipped. Your order details are \nindicated below. If you would like to view the status of your order or make any changes to it, please visit Your Orders on \nAmazon.com. Your digital video games and software purchases will be available in Your Games and Software Library. \nYour purchase has been divided into 3 orders. \nThis order is placed on behalf of U.S. Attorney's Office, SONY. \nOrder Details \nOrder \n#111-2544752-6074601 \nPlaced on today. November 2 \nEFTA00019209\n\nYour guaranteed delivery date is: \nMonday, November 9 \nYour shipping speed: \nsAFREE Shipping \nOrder Details \ne sent to: \nNew York, NY \nUnited States \nDell USB DVD Drive-DW316 \nPersonal Computers \nSold by Amazon.com Services LLC \nCondition: New \n$27.99 \nOrder Total: $27.99 \nThe payment details of your transaction can be found on the order invoice. \nOrder #111 -0303935-3604241 \nPlaced on today. November 2 \nYour estimated delivery date is: \nFriday, \nNovember 6-\nTuesday, November \n10 \nYour shipping speed: \naStandard Shipping \nOrder Details \nYour \norder will be sent to: \nNew York, NY \nUnited States \n2019 Newest HP Pavilion 15 15.6\" HD Touchscreen \nBusiness Laptop Intel Quad-Core i5-8250U  16GB \nDDR4  512GB SSD  Type-C HDMI WiFi AC \nUHD \nWindows 10 \nPersonal Computers \nSold by PConline365 \nCondition: New \n$757.98 \nOrder Total: $757.98 \nThe payment details of your transaction can be found on the order invoice. \nOrder #111-3128522-0349002 \nPlaced on today. November 2 \nDownload and manage your digital video games and software purchases from \nGames and software library \nMicrosoft Office Home and Business 2019 Download 1 \n$219.99 \nPerson Compatible on Windows 10 and Apple MacOS \nEFTA00019210\n\nMicrosoft \nSold by: Amazon.com Services LLC \nOrder Total: $219.99 \nThe payment details of your transaction can be found on the order invoice. \nTo learn more about ordering, go to Ordering  from \nAmazon.com. \nIf you want more information or need more assistance, go to Help. \nWe hope to see you again soon! \nAmazon.com \nTop picks for you \n2019 HP Probook \n450 G6 15.6 \n2019 HP Probook 450 G6 \n15.6\" \nHD Business Laptop...\n$1,099.99 \nSamsung \nElectronics \nUN32N5300AFXZA \n32 \nSamsung  Electronics \nUN32N5300AFXZA 32\" 1080p... \nSee our site \nEpson \nMaintenance Tank \nfor SureColor P \nSeries Large Format \nPrinters \nEpson Maintenance Tank for \nSureColor P Series... \nBy placing your order. you agree toAmazon.corris Privacy Notice and Conditions of Use. Unless otherwise noted. items sold by Amazon.com or \nAmazon Digital Services. Inc. are subject to sales tax in select states in accordance with the applicable laws of that state. If your order contains \none or more items from a seller other than \nAmazon.com\n and/or Amazon Digital Services. Inc.. it may be subject to state and local sales tax. \ndepending upon the seller's business policies and the location of their operations. Learn more about lax and seller information. \nThis email was sent from a notification-only address that cannot accept incoming email. Please do not reply to this message. \nEFTA00019211",
    "pageCount": 5,
    "dataset": "Dataset 8"
  },
  "entities": {
    "people": [
      {
        "name": "Your Amazon",
        "role": "extracted",
        "context": "From: \nTo: \n )1.\nSubject: RE: Your Amazon.com order of \"2019 Newest HP"
      },
      {
        "name": "Metropolitan Correctional",
        "role": "extracted",
        "context": "o just address it to \"Warden, Metropolitan Correctional Center\". \nThanks! \nFrom \nSent"
      },
      {
        "name": "From \nSent",
        "role": "extracted",
        "context": "rrectional Center\". \nThanks! \nFrom \nSent: Tuesday, November 10, 202012"
      },
      {
        "name": "Phone \nBegin",
        "role": "extracted",
        "context": "we discussed. \nSent from my iPhone \nBegin forwarded message: \nFrom: (US"
      },
      {
        "name": "The Maxwell",
        "role": "extracted",
        "context": "P Pavilion and 2 more items. \nThe Maxwell Laptop is ready to be picked"
      },
      {
        "name": "To \nCc",
        "role": "extracted",
        "context": "ay, November 9, 2020 2:11 PM \nTo \nCc: (USANYS) \n(USANYS) < \nSubjec"
      },
      {
        "name": "Phone \nOn",
        "role": "extracted",
        "context": "nks very much, \nSent from my iPhone \nOn Nov 6, 2020, at 11:00 AM, (US"
      },
      {
        "name": "Hi \nThanks",
        "role": "extracted",
        "context": "2 more items. \nEFTA00019208\n\nHi \nThanks again for your help with this"
      },
      {
        "name": "Your \nAccount",
        "role": "extracted",
        "context": "ore items. \nL4.-\nAmazon.c\nam \nYour \nAccount \nAmazon.com \nOrder Confirmati"
      },
      {
        "name": "Order Confirmation",
        "role": "extracted",
        "context": "m \nYour \nAccount \nAmazon.com \nOrder Confirmation \nOrder \n#111-2544752-6074601"
      },
      {
        "name": "Your Orders",
        "role": "extracted",
        "context": "y changes to it, please visit Your Orders on \nAmazon.com. Your digital"
      },
      {
        "name": "Your Games",
        "role": "extracted",
        "context": "urchases will be available in Your Games and Software Library. \nYour p"
      },
      {
        "name": "Software Library",
        "role": "extracted",
        "context": "e available in Your Games and Software Library. \nYour purchase has been divi"
      },
      {
        "name": "Order Details",
        "role": "extracted",
        "context": ".S. Attorney's Office, SONY. \nOrder Details \nOrder \n#111-2544752-6074601"
      },
      {
        "name": "Shipping \nOrder",
        "role": "extracted",
        "context": "Your shipping speed: \nsAFREE Shipping \nOrder Details \ne sent to: \nNew York"
      },
      {
        "name": "Personal Computers",
        "role": "extracted",
        "context": "es \nDell USB DVD Drive-DW316 \nPersonal Computers \nSold by Amazon.com Services"
      },
      {
        "name": "Order Total",
        "role": "extracted",
        "context": "LLC \nCondition: New \n$27.99 \nOrder Total: $27.99 \nThe payment details"
      },
      {
        "name": "Standard Shipping",
        "role": "extracted",
        "context": "r \n10 \nYour shipping speed: \naStandard Shipping \nOrder Details \nYour \norder w"
      },
      {
        "name": "Touchscreen \nBusiness",
        "role": "extracted",
        "context": "ewest HP Pavilion 15 15.6\" HD Touchscreen \nBusiness Laptop Intel Quad-Core i5-825"
      },
      {
        "name": "Laptop Intel",
        "role": "extracted",
        "context": "5.6\" HD Touchscreen \nBusiness Laptop Intel Quad-Core i5-8250U  16GB \nDDR"
      },
      {
        "name": "Microsoft Office",
        "role": "extracted",
        "context": "Games and software library \nMicrosoft Office Home and Business 2019 Downlo"
      },
      {
        "name": "Person Compatible",
        "role": "extracted",
        "context": "ess 2019 Download 1 \n$219.99 \nPerson Compatible on Windows 10 and Apple MacOS"
      },
      {
        "name": "Apple Mac",
        "role": "extracted",
        "context": "Compatible on Windows 10 and Apple MacOS \nEFTA00019210\n\nMicrosoft \nS"
      },
      {
        "name": "Microsoft \nSold",
        "role": "extracted",
        "context": "nd Apple MacOS \nEFTA00019210\n\nMicrosoft \nSold by: Amazon.com Services LLC"
      },
      {
        "name": "Business Laptop",
        "role": "extracted",
        "context": "HP Probook 450 G6 \n15.6\" \nHD Business Laptop...\n$1,099.99 \nSamsung \nElectr"
      },
      {
        "name": "Samsung \nElectronics",
        "role": "extracted",
        "context": "Business Laptop...\n$1,099.99 \nSamsung \nElectronics \nUN32N5300AFXZA \n32 \nSamsung"
      },
      {
        "name": "Samsung  Electronics",
        "role": "extracted",
        "context": "ctronics \nUN32N5300AFXZA \n32 \nSamsung  Electronics \nUN32N5300AFXZA 32\" 1080p..."
      },
      {
        "name": "Epson \nMaintenance",
        "role": "extracted",
        "context": "A 32\" 1080p... \nSee our site \nEpson \nMaintenance Tank \nfor SureColor P \nSeries"
      },
      {
        "name": "Series Large",
        "role": "extracted",
        "context": "enance Tank \nfor SureColor P \nSeries Large Format \nPrinters \nEpson Maint"
      },
      {
        "name": "Format \nPrinters",
        "role": "extracted",
        "context": "for SureColor P \nSeries Large Format \nPrinters \nEpson Maintenance Tank for"
      },
      {
        "name": "Epson Maintenance",
        "role": "extracted",
        "context": "eries Large Format \nPrinters \nEpson Maintenance Tank for \nSureColor P Series."
      },
      {
        "name": "Privacy Notice",
        "role": "extracted",
        "context": "er. you agree toAmazon.corris Privacy Notice and Conditions of Use. Unless"
      },
      {
        "name": "Amazon Digital",
        "role": "extracted",
        "context": "items sold by Amazon.com or \nAmazon Digital Services. Inc. are subject to"
      }
    ],
    "locations": [
      {
        "name": "New York, NY",
        "type": "city"
      }
    ],
    "dates": [
      {
        "date": "2020-11-10",
        "event": "2020-11-10"
      },
      {
        "date": "2020-11-10",
        "event": "November 10, 2020"
      },
      {
        "date": "2020-11-09",
        "event": "November 9, 2020"
      },
      {
        "date": "2020-11-06",
        "event": "November 6, 2020"
      },
      {
        "date": "2020-11-03",
        "event": "November 3, 2020"
      },
      {
        "date": "2020-11-02",
        "event": "November 2, 2020"
      },
      {
        "date": "2020-11-02",
        "event": "November 02 2020"
      }
    ],
    "flights": [],
    "phone_numbers": [
      "111-2544752",
      "111-0303935",
      "111-3128522"
    ],
    "organizations": []
  },
  "processedAt": "2025-12-23T12:25:58.506Z"
}