{
  "document": {
    "id": "efta00019493",
    "filename": "EFTA00019493.pdf",
    "path": "C:\\Users\\user\\CascadeProjects\\epsteinexposed\\apps\\web\\DataSet 8\\VOL00008\\IMAGES\\0003\\EFTA00019493.pdf",
    "text": "\n\nFrom: ' \nD\"<\nTo: Jeff \nJocks <jjocks®sondeeracine.com> \nCc: ' \"  < \n>, I \n(USANYS)\" \nSubject: RE: Subpoena to Interlochen Center for the Arts \nDate: Fri, 26 Mar 2021 19:37:09 +0000 \nAttachments: 2021-03-26,_subpoena_to_Interlochen.pdf \nJeff, \nThanks again for taking the time to speak with me this morning. As we discussed, I'm attaching a subpoena for additional \nstudent records. \nThank you, \nFrom: Jeff Jocks <jjocks@sondeeracine.com> \nSent: Thursday, March 25, 2021 4:41 PM \nTo: \n<> \nCc: \nSubject: Re: Subpoena to Interlochen Center for the Arts \nSounds good. Yes, that is the best number. \nThanks, \nJeff \nJeffrey L. Jocks \nSondee, Racine & Doren, PLC \n310 West Front Street, Suite 300 \nTraverse City, Michigan 49684 \n231-947-0400 \njjocksPsondeeracine.com \nwww.sondeeracine.com \n(USANYS) \nCONFIDENTIALITY NOTICE: The information contained in this email and any attachments is intended for the use of the \naddressee only. Its contents may be privileged, confidential, and exempt from disclosure under applicable law. If you are \nnot the named addressee, please delete it immediately. Thank you. \nFrom: \" \n<\nDate: Thursday, March 25, 2021 at 4:40 PM \nTo: Jeff Jocks \n<jjocks@sondeeracine.com>\nCc: ' )\" \nSubject: RE: Subpoena to Interlochen Center for the Arts \n(USANYS)\" \nEFTA00019493\n\nThanks so much—let's plan to talk at 9:30 tomorrow morning, if that works for you. Is this the best number to reach you \nthen: 231-947-0400 \nThanks, \nFrom: Jeff Jocks \n<jjocksPsondeeracine.com>\nSent: Thursday, March 25, 2021 4:32 PM \nTo: \nCc: \n>; \nSubject: Re: Subpoena to Interlochen Center for the Arts \nI'm available between 9am and 10am, and then again after 11am. \nThanks, \nJeff \nJeffrey L. Jocks \nSondee, Racine & Doren, PLC \n310 West Front Street, Suite 300 \nTraverse City, Michigan 49684 \n231-947-0400 \njjocksPsondeeracine.com \nwww.sondeeracine.com \n(USANYS) \nCONFIDENTIALITY NOTICE: The information contained in this email and any attachments is intended for the use of the \naddressee only. Its contents may be privileged, confidential, and exempt from disclosure under applicable law. If you are \nnot the named addressee, please delete it immediately. Thank you. \nFrom: \" \nDate: Thursday, March 25, 2021 at 3:41 PM \nTo: Jeff Jocks \n<jjocks@sondeeracine.com>\nCc: \"\n  4   \nz \nSubject: RE: Subpoena to Interlochen Center for the Arts \nHi Jeff, \nHope you're doing well. Are you available for a quick call tomorrow morning? \nThanks very much, \nFrom: Jeff Jocks \n<jjocksPsondeeracine.com>\nSent: Thursday, January 7, 2021 11:10 AM \nTo: \nCc: \n>; \nSubject: Re: Subpoena to Interlochen Center for the Arts \n(USANYS) \n(USANYS)\" \nEFTA00019494\n\n231-947-0400 \nJeffrey L. Jocks \nSondee, Racine & Doren, PLC \n310 West Front Street, Suite 300 \nTraverse City, Michigan 49684 \n231-947-0400 \njjocks@sondeeracine.com \nwww.sondeeracine.com \nCONFIDENTIALITY NOTICE: The information contained in this email and any attachments is intended for the use of the \naddressee only. Its contents may be privileged, confidential, and exempt from disclosure under applicable law. If you are \nnot the named addressee, please delete it immediately. Thank you. \nFrom: \" \nDate: Thursday, January 7, 2021 at 10:37 AM \nTo: Jeff Jocks \n<jjocks@sondeeracine com> \nCc: ' \n)\" \nSubject: Re: Subpoena to Interlochen Center for the Arts \nHi Jeff— what is the best number to reach you this morning? Thanks. \nSent from my iPhone \nOn Jan 5, 2021, at 3:21 PM, Jeff Jocks <jjocks@sondeeracine.com> wrote: \nThat works for me. \nJeff \nJeffrey L. Jocks \nSondee, Racine & Doren, PLC \n310 West Front Street, Suite 300 \nTraverse City, Michigan 49684 \n231-947-0400 \njjocks@sondeeracine.com \nwww.sondeeracine.com \n(USANYS)\" \nCONFIDENTIALITY NOTICE: The information contained in this email and any attachments is intended for the use of the \naddressee only. Its contents may be privileged, confidential, and exempt from disclosure under applicable law. If you \nare not the named addressee, please delete it immediately. Thank you. \nFrom: \" \nDate: Monday, January 4, 2021 at 8:28 PM \nTo: Jeff Jocks \n<jjocks(thsondeeracine.com>\nCc: ' )\" (USANYS)\" \nEFTA00019495\n\nSubject: Re: Subpoena to Interlochen Center for the Arts \nThat would be great, thanks. Would Thursday at 11:30 work for you? \nSent from my iPhone \nOn Jan 4, 2021, at 3:50 PM, Jeff Jocks <jjocks@sondeeracine.com> wrote: \nSure. Does Wednesday or Thursday morning work? \nJeffrey L. Jocks \nSondee, Racine & Doren, PLC \n310 West Front Street, Suite 300 \nTraverse City, Michigan 49684 \n231-947-0400 \njjocks@sondeeracine.com \nwww.sondeeracine.com \nCONFIDENTIALITY NOTICE: The information contained in this email and any attachments is intended for the use of the \naddressee only. Its contents may be privileged, confidential, and exempt from disclosure under applicable law. If you \nare not the named addressee, please delete it immediately. Thank you. \nFrom: ' \nyi \nDate: Monday, January 4, 2021 at 1:02 PM \nTo: Jeff Jocks <jjocks@sondeeracine.com>\nCc:'1 \n4   \nSubject: RE: Subpoena to Interlochen Center for the Arts \nHi Jeff, \n(USANYS)\" \nThanks very much. Are you available for a call sometime in the next few weeks? We have one or two follow up \nquestions that would be helpful to talk through. \nThanks, \nFrom: Jeff Jocks \n<iiocksPsondeeracine.com>\nSent: Wednesday, December 30, 2020 2:37 PM \nTo: \n) \nCc: \nI • \n(USANYS) \nSubject: Re: Subpoena to Interlochen Center for the Arts \nSorry about the delay. Interlochen doesn't have any other documents regarding tuition payment information or \npayments by Epstein or Epstein entities. \nLet me know if you have any other questions. \nEFTA00019496\n\nThanks, \nJeff Jocks \nJeffrey L. Jocks \nSondee, Racine & Doren, PLC \n310 West Front Street, Suite 300 \nTraverse City, Michigan 49684 \n231-947-0400 \njjocksasondeeracine.com \nwww.sondeeracine.com \nCONFIDENTIALITY NOTICE: The information contained in this email and any attachments is intended for the use of the \naddressee only. Its contents may be privileged, confidential, and exempt from disclosure under applicable law. If you \nare not the named addressee, please delete it immediately. Thank you. \nFrom: \n)\" \nDate: Monday, December 7, 2020 at 11:27 AM \nTo: Jeff Jocks \n<jjocks@sondeeracine.com>\nCc: \" \nSubject: RE: Subpoena to Interlochen Center for the Arts \nHi Jeff, \nJust checking in on the below. \nThanks, \nFrom: \nSent: Monday, November 16, 2020 3:28 PM \nTo: Jeff Jocks \n<jjocksPsondeeracine.com>\nCc: j >; \nSubject: RE: Subpoena to Interlochen Center for the Arts \nHi Jeff, \n(USANYS) \n(USANYS)\" \nHope you're doing well. I'm following up on our conversation from earlier this month to see if you have any updates on \nthe categories of documents we discussed. \nThanks very much, \nFrom: Jeff Jocks \n<ijocksf&sondeeracine.com>\nSent: Friday, October 30, 2020 11:15 AM \nTo:\nCc: \nI \nSubject: Re: Subpoena to Interlochen Center for the Arts \n>; \n(USANYS) \nThat works for me. I will call in at 10am Monday. \nEFTA00019497\n\nThanks, \nJeff \nJeffrey L. Jocks \nSondee, Racine & Doren, PLC \n310 West Front Street, Suite 300 \nTraverse City, Michigan 49684 \n231-947-0400 \njjocksPsondeeracine.com \nwww.sondeeracine.com \nCONFIDENTIALITY NOTICE: The information contained in this email and any attachments is intended for the use of the \naddressee only. Its contents may be privileged, confidential, and exempt from disclosure under applicable law. If you \nare not the named addressee, please delete it immediately. Thank you. \nFrom: ' \n)\" \nDate: Friday, October 30, 2020 at 11:13 AM \nTo: Jeff \nJocks <jjocks@sondeeracine corn> \nCc:\nSubject: Re: Subpoena to Interlochen Center for the Arts \nHi \nJeff, \n(USANYS)\" \nThanks very much. Would a call on Monday at 10 a.m. work for you? If so, we can use this conference line: \nThanks, \nAlison \nSent from my iPhone \nOn Oct 30, 2020, at 9:06 AM, Jeff Jocks <jjocksPsondeeracine.com> wrote: \nHi Maurene — \nI'm happy to have a call. I'm available Monday all morning, Tuesday until 10:30am and Wednesday all morning. \nI apologize about not getting back with you. I thought the other attorney that filed the response was going to do so. \nRegardless, the response included everything that Interlochen has. They only keep tuition payment information for 7 \nyears and nothing in their files reflects any payments by Epstein or Epstein entities. \nThanks, \nJeff \nJeffrey L. Jocks \nSondee, Racine & Doren, PLC \n310 West Front Street, Suite 300 \nTraverse City, Michigan 49684 \n231-947-0400 \nEFTA00019498\n\njjocksPsondeeracine.com \nwww.sondeeracine.com \nCONFIDENTIALITY NOTICE: The information contained in this email and any attachments is intended for the use of \nthe addressee only. Its contents may be privileged, confidential, and exempt from disclosure under applicable law. \nIf you are not the named addressee, please delete it immediately. Thank you. \nFrom: \" \nDate: Thursday, October 29, 2020 at 6:20 PM \nTo: Jeff Jocks locks(asondeeracine.com>\nCc: \" \nSubject: RE: Subpoena to Interlochen Center for the Arts \nJeff, \n(USANYS)\" \nI hope you are doing well. We still have not received a response to our inquiry from April of 2020. Would you be \navailable for a call with our team next week to discuss, please? \nThanks, \nAssistant United States Attorney \nSouthern District of New York \nI  St. Andrew's Plaza \nNew York, NY 10007 \n212-637-2324 \nFrom: \nSent: Wednesday, April 8, 2020 1:46 PM \nTo: Jeff Jocks \n<jjocksPsondeeracine.com>\nSubject: RE: Subpoena to Interlochen Center for the Arts \nHi Jeff, \nNo, I don't think you responded. Totally understandable given everything that has gone on in the last month. I'd still \nbe grateful if you could get back to me on this point, please. \nHope you are also staying safe and healthy. \nThanks, \nAssistant United States Attorney \nEFTA00019499\n\nSouthern District of New York \nI  St. Andrew's Plaza \nNew York, NY 10007 \n212-637-2324 \nFrom: Jeff Jocks locksf@sondeeracine.com>\nSent: Wednesday, April 8, 2020 1:20 PM \nTo: \nSubject: Re: Subpoena to Interlochen Center for the Arts \nH \nDid we ever respond to you on this question? Things have gotten so complicated that I can't remember or \ndetermine. \nHope you are staying safe and healthy. \nThanks, \nJeff \nJeffrey L. Jocks \nSondee, Racine & Doren, PLC \n310 West Front Street, Suite 300 \nTraverse City, Michigan 49684 \n231-947-0400 \njjocksPsondeeracine.com \nwww.sondeeracine.com \nCONFIDENTIALITY NOTICE: The information contained in this email and any attachments is intended for the use of \nthe addressee only. Its contents may be privileged, confidential, and exempt from disclosure under applicable law. \nIf you are not the named addressee, please delete it immediately. Thank you. \nFrom: \" \nDate: Sunday, March 8, 2020 at 3:04 PM \nTo: Jeff Jocks <jjocks@sondeeracine.com>  \"Donnini, George B.\" \n<donnini@butzel.com>\nCc: '' \nSubject: RE: Subpoena to Interlochen Center for the Arts \nJeff and George, \nI' \nThank you both very much for your assistance in response to our subpoenas seeking records from Interlochen. In \nreviewing the documents you produced in response to the attached subpoena, a follow-up question arose. Would \nyou please confirm that your production included all records of any tuition payments that Epstein (or his entities) \nmade for any students at Interlochen? \nOur team is also happy to discuss this inquiry over the phone if that would be useful. I am starting a trial tomorrow \nand will have limited availability this week, but my colleagues and (both cc'd) should be \nable to coordinate with you as needed. \nEFTA00019500\n\nBest, \nAssistant United States Attorney \nSouthern District of New York \nSt. Andrew's Plaza \nNew York, NY 10007 \n212-637-2324 \nFrom: Jeff Jocks \n<jjocksPsondeeracine.com>\nSent: Thursday, February 6, 2020 2:46 PM \nTo: \nCc: \n< \nSubject: Re: Subpoena to Interlochen Center for the Arts \nReceipt confirmed. \nThanks, \nJeff \nJeffrey L. Jocks \nSondee, Racine & Doren, PLC \n310 West Front Street, Suite 300 \nTraverse City, Michigan 49684 \n231-947-0400 \njjocksPsondeeracine.com \nwww.sondeeracine.com \nCONFIDENTIALITY NOTICE: The information contained in this email and any attachments is intended for the use of \nthe addressee only. Its contents may be privileged, confidential, and exempt from disclosure under applicable law. \nIf you are not the named addressee, please delete it immediately. Thank you. \nFrom: \" \nDate: Thursday, February 6, 2020 at 1:51 PM \nTo: Jeff Jocks \n<flocks@sondeeracine.com>\nCc: \" \nSubject: Subpoena to Interlochen Center for the Arts \nJeff, \nAs discussed, attached please find a subpoena addressed to Interlochen seeking information regarding Jeffrey \nEpstein and Ghislaine Maxwell. Per our conversation, we understand that Interlochen will keep this request \nconfidential. \nEFTA00019501\n\nPlease let me know if you have any questions or would like to discuss further. \nBest, \nAssistant United States Attorney \nSouthern District of New York \n1  St. Andrew's Plaza \nNew York, NY 10007 \n212-637-2324 \nEFTA00019502",
    "pageCount": 10,
    "dataset": "Dataset 8"
  },
  "entities": {
    "people": [
      {
        "name": "Ghislaine Maxwell",
        "role": "extracted",
        "context": "eeking information regarding Jeffrey \nEpstein and Ghislaine Maxwell. Per our conversation, we understand that Interlo"
      },
      {
        "name": "Jeff \nJocks",
        "role": "extracted",
        "context": "From: ' \nD\"<\nTo: Jeff \nJocks <jjocks®sondeeracine.com> \nCc"
      },
      {
        "name": "Interlochen Center",
        "role": "extracted",
        "context": "S)\" \nSubject: RE: Subpoena to Interlochen Center for the Arts \nDate: Fri, 26 M"
      },
      {
        "name": "Arts \nDate",
        "role": "extracted",
        "context": "to Interlochen Center for the Arts \nDate: Fri, 26 Mar 2021 19:37:09 +0"
      },
      {
        "name": "Jeff Jocks",
        "role": "extracted",
        "context": "t records. \nThank you, \nFrom: Jeff Jocks <jjocks@sondeeracine.com> \nSe"
      },
      {
        "name": "Arts \nSounds",
        "role": "extracted",
        "context": "to Interlochen Center for the Arts \nSounds good. Yes, that is the best n"
      },
      {
        "name": "Jeff \nJeffrey",
        "role": "extracted",
        "context": "is the best number. \nThanks, \nJeff \nJeffrey L. Jocks \nSondee, Racine & Do"
      },
      {
        "name": "Jocks \nSondee",
        "role": "extracted",
        "context": "r. \nThanks, \nJeff \nJeffrey L. Jocks \nSondee, Racine & Doren, PLC \n310 Wes"
      },
      {
        "name": "West Front",
        "role": "extracted",
        "context": "dee, Racine & Doren, PLC \n310 West Front Street, Suite 300 \nTraverse C"
      },
      {
        "name": "Traverse City",
        "role": "extracted",
        "context": "West Front Street, Suite 300 \nTraverse City, Michigan 49684 \n231-947-0400"
      },
      {
        "name": "Arts \nHi",
        "role": "extracted",
        "context": "to Interlochen Center for the Arts \nHi Jeff, \nHope you're doing well"
      },
      {
        "name": "Phone \nOn",
        "role": "extracted",
        "context": "rning? Thanks. \nSent from my iPhone \nOn Jan 5, 2021, at 3:21 PM, Jeff"
      },
      {
        "name": "Arts \nThat",
        "role": "extracted",
        "context": "to Interlochen Center for the Arts \nThat would be great, thanks. Would"
      },
      {
        "name": "Would Thursday",
        "role": "extracted",
        "context": "That would be great, thanks. Would Thursday at 11:30 work for you? \nSent"
      },
      {
        "name": "Does Wednesday",
        "role": "extracted",
        "context": "ndeeracine.com> wrote: \nSure. Does Wednesday or Thursday morning work? \nJe"
      },
      {
        "name": "Arts \nSorry",
        "role": "extracted",
        "context": "to Interlochen Center for the Arts \nSorry about the delay. Interlochen"
      },
      {
        "name": "Alison \nSent",
        "role": "extracted",
        "context": "is conference line: \nThanks, \nAlison \nSent from my iPhone \nOn Oct 30, 20"
      },
      {
        "name": "Hi Maurene",
        "role": "extracted",
        "context": "cksPsondeeracine.com> wrote: \nHi Maurene — \nI'm happy to have a call."
      },
      {
        "name": "Arts \nJeff",
        "role": "extracted",
        "context": "to Interlochen Center for the Arts \nJeff, \n(USANYS)\" \nI hope you are d"
      },
      {
        "name": "Assistant United",
        "role": "extracted",
        "context": "to discuss, please? \nThanks, \nAssistant United States Attorney \nSouthern Dis"
      },
      {
        "name": "States Attorney",
        "role": "extracted",
        "context": "e? \nThanks, \nAssistant United States Attorney \nSouthern District of New Yor"
      },
      {
        "name": "Southern District",
        "role": "extracted",
        "context": "stant United States Attorney \nSouthern District of New York \nI  St. Andrew's"
      },
      {
        "name": "Plaza \nNew",
        "role": "extracted",
        "context": "of New York \nI  St. Andrew's Plaza \nNew York, NY 10007 \n212-637-2324"
      },
      {
        "name": "Arts \nReceipt",
        "role": "extracted",
        "context": "to Interlochen Center for the Arts \nReceipt confirmed. \nThanks, \nJeff \nJe"
      },
      {
        "name": "Jeffrey \nEpstein",
        "role": "extracted",
        "context": "seeking information regarding Jeffrey \nEpstein and Ghislaine Maxwell. Per ou"
      }
    ],
    "locations": [
      {
        "name": "New York, NY",
        "type": "city"
      }
    ],
    "dates": [
      {
        "date": "2021-03-26",
        "event": "2021-03-26"
      },
      {
        "date": "2021-03-25",
        "event": "March 25, 2021"
      },
      {
        "date": "2021-01-07",
        "event": "January 7, 2021"
      },
      {
        "date": "2021-01-04",
        "event": "January 4, 2021"
      },
      {
        "date": "2020-12-30",
        "event": "December 30, 2020"
      },
      {
        "date": "2020-12-07",
        "event": "December 7, 2020"
      },
      {
        "date": "2020-11-16",
        "event": "November 16, 2020"
      },
      {
        "date": "2020-10-30",
        "event": "October 30, 2020"
      },
      {
        "date": "2020-10-29",
        "event": "October 29, 2020"
      },
      {
        "date": "2020-04-08",
        "event": "April 8, 2020"
      },
      {
        "date": "2020-03-08",
        "event": "March 8, 2020"
      },
      {
        "date": "2020-02-06",
        "event": "February 6, 2020"
      }
    ],
    "flights": [],
    "phone_numbers": [
      "231-947-0400",
      "212-637-2324"
    ],
    "organizations": []
  },
  "processedAt": "2025-12-23T12:25:59.026Z"
}