{
  "document": {
    "id": "efta00023274",
    "filename": "EFTA00023274.pdf",
    "path": "C:\\Users\\user\\CascadeProjects\\epsteinexposed\\apps\\web\\DataSet 8\\VOL00008\\IMAGES\\0004\\EFTA00023274.pdf",
    "text": "\n\nFrom: \"    )\"  \nTo:' \nSubject: FW: travel approval request \nDate: Thu, 13 Feb 2020 18:47:01 +0000 \nImportance: High \nInline-Images: image001.png \nr     \nThis is the flight I just asked to book for me, FYI. \nFrom: \nSent: Thursday, February 13, 2020 1:46 PM \nTo: \nCc: \nSubject: RE: travel approval request \nImportance: High \n) \n, the Delta departing flight you chose leaving LGA at 9:00am, arriving in Pensacola, FL at 12:49pm is not refundable, so \nyou'll need to choose another flight option. While checking out your flight options, I found a  flight that will get you into \nPensacola, FL around the same time as your preferred option that's fully refundable. The difference is that the flight \nleaves at 8:11am instead of 9:00am. I've placed the departing flight below for your review. \nArnericantkirlines \nContract carrier \n•  Feb 19 \naw York, NY (LGA), 8:11 AM \niarlotte, NC (CLT), 10:35 AM \nmiles \n1252 \nach Lowest available including Penalty fares. \nrbus A319 \neview seat map \nLayover (55m) \nCharlotte, NC (CLT) \nAmericanAirlines\\ \nContract carrier \nM, Feb 19 \niarlotte, NC (CLT), 11:30 AM \nmsacola, FL (PNS), 12:23 PM \nIC  miles \n5298 (Operated by PSA AIRLINES AS AMERICAN \n\\GLE) \nach Lowest available including Penalty fares. \nRJ900 \neview seat map \nTop of Form \nAll available fares for Option 28 \n$161.70 \nGovt contract fare limited availability \nBottom of Form \nPlease let me know if you would like me to reserve this flight instead and I'll continue with your reservation. Thanks as \nalways. \nEFTA00023274\n\nU.S. Attorney's Office (SONY) \nLegal Assistant, Public Corruption \nFrom: \nSent: Thursday, February 13, 2020 1:26 PM \nTo: \nCc: \nSubject: RE: travel approval request \n< \nApologies for the slight delay yesterday on this travel, we had a witness scheduling issue so the travel will be a day later \nthan originally anticipated. The city is Pensacola, Florida, and it will be me and (rather than and \nif you could please book me on the following flights: \nFeb. 19: Delta, LGA to PNS, 9:00 a.m. (arriving 12:49 p.m.) \nFeb. 20: Delta, PNS to LGA, 4:06 p.m. (arriving 9:41 p.m.) \nAnd the following hotel, for the night of Feb. 19: \n- Hilton Garden Inn (listed in E2 as \"HGI PENSACOLA AIRPORT MEDICAL\") \nWe will also need a conference room at the Hilton Garden Inn for February 19, starting at 5:00 p.m. for three hours (or for \nthe entire day, if that's the only way they'll do it). \nPlease let us know if any questions or issues, and thanks as always. \nFrom: \nSent: Wednesday, February 12, 2020 09:02 \nTo: \nCc: \nSubject: Re: travel approval request \nHi, \nWhich specific city will the hotel be in? \nIf could push the travel authorizations thru to • & I today, that would be great.... As well as sending the \nconference room payment request to \nRemember to take the FL tax exempt form along with you. \nThanks \n>; \n•c> \nSent from my iPhone \nOn Feb 12, 2020, at 6:43 AM, \n> \nwrote: \nEFTA00023275\n\nApproved \nSent from my iPad \nOn Feb 11, 2020, at 7:53 PM, \n) \n< \nwrote: \nS \nSimilar to prior requests in connection with the Epstein investigation (2018R01618), and I would like to please \nrequest permission for the two of us to travel next week for an interview of a witness in Pensacola, Florida on 2/19. \nWe'd plan to fly down on 2/18 and fly back on 2/19. Also, similar to prior requests, we'd like to request approval to get \na conference room on 2/19. \nThank you, \nFrom: \nSent: Tuesday, January 21, 2020 2:56 PM \nTo: \nCc: \nSubject: RE: travel approval request \nApproved \nFrom: \nSent: Tuesday, January 21, 2020 2:49 PM \nTo: \nCc: \nSubject: RE: travel approval request \nS \nSimilar to prior requests in connection with the Epstein investigation (2018R01618), but with an added international \nelement, we'd like to please request permission for the team to travel next week for an interview near Stockholm, \nSweden, next week on January 29th and/or 30th. We expect to be traveling, respectively, some combination of the \n27th (overnight) to the 31st, depending on when the interview ends up being scheduled, and we'll put final dates on \nour formal applications. Also similar to prior trips, we'd like to request approval to get a conference room for one of \nthose days at a hotel for the interview itself. \nAlso based on our discussion earlier we'll be mindful of looking for domestic (or domestic-flagged) carrier flights, as \nwell as the costs of any alternatives, in looking at possible specific bookings. Thanks as always for your help and input \non that. \nthank you, \nFrom: \nSent: Wednesday, December 11, 2019 09:58 \nTo: \nEFTA00023276\n\nCc: \nSubject: RE: travel approval request \na \nSimilar to prior requests in connection with the Epstein investigation (2018R01618), we'd like to please request \npermission for the team to travel next week for an interview (or possibly interviews) in Los Angeles on December 16 \nand/or 17. We expect to be traveling, respectively, some combination of the 15th to the 18th. Also similar to prior \ntrips, we'd like to request approval to get a conference room for one of those days. \nthank you, \nFrom: \nSent: Tuesday, November 05, 2019 16:53 \nTo: \nCc: \nSubject: RE: travel approval request \nU \nSimilar to prior requests in connection with the Epstein investigation (2018R01618), we'd like to please request \npermission for the team to travel next week for an interview in Los Angeles on November 14. We expect to be \ntraveling, respectively, some combination of the 13th to the 15th (and no conference room necessary for this trip). \nthanks, \nFrom: \nSent: Tuesday, October 22, 2019 13:55 \nTo: \nCc: \nI< \nSubject: RE: travel approval request \nU \nSimilar to prior requests in connection with the Epstein investigation (2018R01618), we'd like to please request \npermission to travel next week for an interview in West Palm Beach on November 4. It will just be me and \nand we'll travel some combination of the 3rd to the 5th. And also same as last time, we'd like to ask permission to \nreserve a conference room at the hotel on that Monday for the interview, please. \nthanks very much, \nFrom: \nSent: Wednesday, June 12, 2019 14:51 \nTo: \nEFTA00023277\n\nCc: \nSubject: RE: travel approval request \na \nAgain in connection with the Epstein investigation (2018R01618), we'd like to please request permission to travel next \nweek for a victim interview in Los Angeles. As of now we tentatively expect to fly down Wednesday and return no \nlater than Friday (and will keep the timeframe as short as scheduling allows). The trip will be some combination of me, \nM, and/or as previously. And also same as last time, we'd like to ask permission to reserve a conference \nroom at the hotel on Thursday for the interview, please. \nthanks very much, \nFrom: \nSent: Friday, May 24, 2019 14:57 \nTo: \nCc: \n<M> \nSubject: RE: travel approval request \nS \n) \nAgain in connection with the Epstein investigation, we'd like to please request permission to travel for approximately \nthree days next week for meetings and interviews in West Palm Beach, Florida. As of now we tentatively expect to fly \ndown Tuesday night and return on Wednesday or Thursday (and will keep the timeframe as short as scheduling \nallows). \nUnfortunately we're still trying to pin down timing for interviewing the victims, so depending on the timing it will \neither be me and or and but we wanted to ask for permission now either way so we weren't \ndoing it super last minute after the holiday on Tuesday. And also same as last time, we'd like to ask permission to \nreserve a conference room at the hotel for the interviews, please. \nthanks very much, \nFrom: \nSent: Wednesday, April 03, 2019 20:57 \nTo: \nSubject: RE: travel approval request \nThank \nyou \nFrom: \nSent: Wednesday, April 03, 2019 20:46 \nTo: \nCc: \nc>; \nSubject: Re: travel approval request \n> \nApproved \nEFTA00023278\n\nSent from my iPad \nOn Apr 3, 2019, at 8:02 PM, \nS \n> \nwrote: \nFor the same case as below, United States v. Epstein, 2018R01618, an investigation relating to enticement of minors \nfor sexual activity, and I would like to please request permission to travel for approximately three days next \nweek for meetings and interviews in West Palm Beach, Florida. As of now we tentatively expect to fly down Tuesday \nnight and return on Friday, though we will shorten the timeframe if scheduling allows. \nPlease let us know if any other information would be helpful, and thanks very much. \nFrom: \nSent: Thursday, March 14, 2019 18:32 \nTo: \nCc: \nSubject: travel approval request \nS \nand I would like to please request permission for travel for United States v. Epstein, 2018801618, an \ninvestigation relating to enticement of minors for sexual activity, for two days of meetings and interviews in West \nPalm Beach and/or Fort Lauderdale, Florida. As of now we're hoping to fly down next Wednesday night and return \non Saturday. \nPlease let us know if any other information would be helpful, and thanks as always. \nAssistant U.S. Attorney \nSouthern District of New York \nEFTA00023279",
    "pageCount": 6,
    "dataset": "Dataset 8"
  },
  "entities": {
    "people": [
      {
        "name": "High \nInline",
        "role": "extracted",
        "context": "0 18:47:01 +0000 \nImportance: High \nInline-Images: image001.png \nr"
      },
      {
        "name": "Arnericantkirlines \nContract",
        "role": "extracted",
        "context": "light below for your review. \nArnericantkirlines \nContract carrier \n•  Feb 19 \naw York,"
      },
      {
        "name": "Form \nAll",
        "role": "extracted",
        "context": "RJ900 \neview seat map \nTop of Form \nAll available fares for Option 28"
      },
      {
        "name": "Form \nPlease",
        "role": "extracted",
        "context": "mited availability \nBottom of Form \nPlease let me know if you would like"
      },
      {
        "name": "Legal Assistant",
        "role": "extracted",
        "context": ".S. Attorney's Office (SONY) \nLegal Assistant, Public Corruption \nFrom: \nSe"
      },
      {
        "name": "Public Corruption",
        "role": "extracted",
        "context": "fice (SONY) \nLegal Assistant, Public Corruption \nFrom: \nSent: Thursday, Febru"
      },
      {
        "name": "Hilton Garden",
        "role": "extracted",
        "context": "for the night of Feb. 19: \n- Hilton Garden Inn (listed in E2 as \"HGI PEN"
      },
      {
        "name": "Phone \nOn",
        "role": "extracted",
        "context": "hanks \n>; \n•c> \nSent from my iPhone \nOn Feb 12, 2020, at 6:43 AM, \n>"
      },
      {
        "name": "Approved \nSent",
        "role": "extracted",
        "context": "AM, \n> \nwrote: \nEFTA00023275\n\nApproved \nSent from my iPad \nOn Feb 11, 2020"
      },
      {
        "name": "Pad \nOn",
        "role": "extracted",
        "context": "3275\n\nApproved \nSent from my iPad \nOn Feb 11, 2020, at 7:53 PM, \n)"
      },
      {
        "name": "Approved \nFrom",
        "role": "extracted",
        "context": "RE: travel approval request \nApproved \nFrom: \nSent: Tuesday, January 21,"
      },
      {
        "name": "West Palm",
        "role": "extracted",
        "context": "next week for an interview in West Palm Beach on November 4. It will"
      },
      {
        "name": "West \nPalm",
        "role": "extracted",
        "context": "of meetings and interviews in West \nPalm Beach and/or Fort Lauderdale,"
      },
      {
        "name": "Fort Lauderdale",
        "role": "extracted",
        "context": "ws in West \nPalm Beach and/or Fort Lauderdale, Florida. As of now we're hop"
      },
      {
        "name": "Attorney \nSouthern",
        "role": "extracted",
        "context": "ks as always. \nAssistant U.S. Attorney \nSouthern District of New York \nEFTA000"
      }
    ],
    "locations": [
      {
        "name": "Palm Beach",
        "type": "location"
      },
      {
        "name": "LGA",
        "type": "airport"
      },
      {
        "name": "Pensacola, FL",
        "type": "city"
      },
      {
        "name": "York, NY",
        "type": "city"
      },
      {
        "name": "Charlotte, NC",
        "type": "city"
      }
    ],
    "dates": [
      {
        "date": "2020-02-13",
        "event": "February 13, 2020"
      },
      {
        "date": "2020-02-12",
        "event": "February 12, 2020"
      },
      {
        "date": "2020-01-21",
        "event": "January 21, 2020"
      },
      {
        "date": "2019-12-11",
        "event": "December 11, 2019"
      },
      {
        "date": "2019-11-05",
        "event": "November 05, 2019"
      },
      {
        "date": "2019-10-22",
        "event": "October 22, 2019"
      },
      {
        "date": "2019-06-12",
        "event": "June 12, 2019"
      },
      {
        "date": "2019-05-24",
        "event": "May 24, 2019"
      },
      {
        "date": "2019-04-03",
        "event": "April 03, 2019"
      },
      {
        "date": "2019-03-14",
        "event": "March 14, 2019"
      }
    ],
    "flights": [
      {
        "from": "LGA",
        "to": "PNS",
        "date": "unknown",
        "passengers": []
      },
      {
        "from": "PNS",
        "to": "LGA",
        "date": "unknown",
        "passengers": []
      }
    ],
    "phone_numbers": [
      "2018801618"
    ],
    "organizations": []
  },
  "processedAt": "2025-12-23T12:26:08.611Z"
}