{
  "document": {
    "id": "efta00013987",
    "filename": "EFTA00013987.pdf",
    "path": "C:\\Users\\user\\CascadeProjects\\epsteinexposed\\apps\\web\\DataSet 8\\VOL00008\\IMAGES\\0001\\EFTA00013987.pdf",
    "text": "\n\nEvent: Epstein/call in from \nStart Date: 2008-06-13 14:00:00 +0000 \nEnd Date: 2008-06-13 14:30:00 +0000 \nOrganizer: \n) \nLocation: ofc. \nClass: X-PERSONAL \nDate Created: 2017-04-04 01:32:50 +0000 \nDate Modified: 2017-04-04 01:32:50 +0000 \nPriority: 5 \nDTSTAMP: 2008-06-11 15:27:38 +0000 \nAttendee:\n> \nWhen: Friday, June 13, 2008 10:00 AM-10:30 AM (GMT-05:00) Eastern Time (US & Canada). \nWhere: ofc. \n*     * * * * * * * \n*  * \nyou can participate by phone. Let me know best number, Thanks, \n  Original Message \nFrom: (USAFLS) \nTo: \nCc: . (ODAG) (SMO) \nSent: Wed Jun 11 10:29:23 2008 \nSubject: RE: Epstein \nSpoke with \n(305) 961-9299. \n(ODAG) (SMO) \n.  Everyone is good for 10:00 this Friday morning. will be calling= office \nFrom: \nSent: Wednesday, June 11, 2008 10:21 AM \nTo: (USAFLS); (ODAG) (SMO) \nCc: . (ODAG) (SMO) \nSubject: RE: Epstein \nEFTA00013987\n\nI'm available anytime \nFrom: (USAFLS) \nSent: Wednesday, June 11, 2008 10:09 AM \nTo: (ODAG) (SMO); \nCc: . (ODAG) (SMO) \nSubject: RE: Epstein \nAbsolutely, I'm available from 10 to 11 and after 11 have a conflict. \nFrom: (ODAG) (SMO) \nSent: Wednesday, June 11, 2008 10:02 AM \nTo: (USAFLS) \nCc: (ODAG) (SMO) \nSubject: Epstein \nWould you guys be available Friday morning by telephone to discuss? \nEFTA00013988",
    "pageCount": 2,
    "dataset": "Dataset 8"
  },
  "entities": {
    "people": [
      {
        "name": "Start Date",
        "role": "extracted",
        "context": "Event: Epstein/call in from \nStart Date: 2008-06-13 14:00:00 +0000 \nE"
      },
      {
        "name": "End Date",
        "role": "extracted",
        "context": "e: 2008-06-13 14:00:00 +0000 \nEnd Date: 2008-06-13 14:30:00 +0000 \nO"
      },
      {
        "name": "Date Created",
        "role": "extracted",
        "context": "ion: ofc. \nClass: X-PERSONAL \nDate Created: 2017-04-04 01:32:50 +0000 \nD"
      },
      {
        "name": "Date Modified",
        "role": "extracted",
        "context": "d: 2017-04-04 01:32:50 +0000 \nDate Modified: 2017-04-04 01:32:50 +0000 \nP"
      },
      {
        "name": "Eastern Time",
        "role": "extracted",
        "context": "10:00 AM-10:30 AM (GMT-05:00) Eastern Time (US & Canada). \nWhere: ofc."
      },
      {
        "name": "Original Message",
        "role": "extracted",
        "context": "know best number, Thanks, \n  Original Message \nFrom: (USAFLS) \nTo: \nCc: . ("
      },
      {
        "name": "Wed Jun",
        "role": "extracted",
        "context": "o: \nCc: . (ODAG) (SMO) \nSent: Wed Jun 11 10:29:23 2008 \nSubject: RE"
      },
      {
        "name": "Epstein \nSpoke",
        "role": "extracted",
        "context": "1 10:29:23 2008 \nSubject: RE: Epstein \nSpoke with \n(305) 961-9299. \n(ODAG)"
      },
      {
        "name": "Epstein \nAbsolutely",
        "role": "extracted",
        "context": ". (ODAG) (SMO) \nSubject: RE: Epstein \nAbsolutely, I'm available from 10 to 11"
      },
      {
        "name": "Epstein \nWould",
        "role": "extracted",
        "context": ") \nCc: (ODAG) (SMO) \nSubject: Epstein \nWould you guys be available Friday"
      }
    ],
    "locations": [],
    "dates": [
      {
        "date": "2008-06-13",
        "event": "2008-06-13"
      },
      {
        "date": "2017-04-04",
        "event": "2017-04-04"
      },
      {
        "date": "2008-06-11",
        "event": "2008-06-11"
      },
      {
        "date": "2008-06-13",
        "event": "June 13, 2008"
      },
      {
        "date": "2008-06-11",
        "event": "June 11, 2008"
      }
    ],
    "flights": [],
    "phone_numbers": [
      "(305) 961-9299"
    ],
    "organizations": []
  },
  "processedAt": "2025-12-23T12:25:47.877Z"
}