{
  "document": {
    "id": "efta00009915",
    "filename": "EFTA00009915.pdf",
    "path": "C:\\Users\\user\\CascadeProjects\\epsteinexposed\\apps\\web\\DataSet 8\\VOL00008\\IMAGES\\0001\\EFTA00009915.pdf",
    "text": "\n\nEvent: FW: Epstein Estate \nStart Date: 2020-11-09 21:30:00 +0000 \nEnd Date: 2020-11-09 22:00:00 +0000 \nOrganizer: Weinstein, Marc A. \nLocation: Skype Meeting; Conference ID: 570 579 045; \nClass: X-PERSONAL \nDate Created: 2020-11-09 21:58:35 +0000 \nDate Modified: 2020-11-09 21:58:35 +0000 \nPriority: 5 \nDTSTAMP: 2020-11-09 15:30:14 +0000 \nAttendee: \n Original Appointment \nFrom: Weinstein, Marc A. \nSent: Monday, November 9, 2020 10:35 AM \nTo: Weinstein, Marc A.; Andrew Tomback \nSubject: Epstein Estate \nWhen: Monday, November 9, 2020 4:30 PM-5:00 PM (UTC-05:00) Eastern Time (US & Canada). \nWhere: Skype Meeting; Conference ID: 570 579 045; \nDial-In Information (for meetings with no presentations or video) \nDial-In Number: \nConference ID: \nOne touch dial-\nAdditional Dial-\nBrazil \n+1 (201) 630-0824 \n570579045 \nin from mobile phone (via cellular service) \nIn Numbers \n+55 11 3181-5692 \nCanada +1 647-749-1240 \nChina +86 400 842 8305 \nFrance +33 1 73 24 04 53 \nGermany +49 69 667737017 \nIndia +91 22 6001 6148 \nIreland +353 1 566 1143 \nIsrael +972 3 3762055 \nEFTA00009915\n\nJapan +81 3-4510-7259 \nKorea (Seoul) +82 70-7488-2208 \nSingapore +65 3157 0147 \nUnited Kingdom +44 20 3443 6288 \nUnited States +1 (201) 630-0824 \nFull list of dial-in numbers \nMeetings with a presentation or video \nConnect from computer or mobile device (via network/internet connection) \nHelp \nTry Skype Web App if you are having trouble joining \nJoining from a computer using the \"Connect from computer or mobile device\" link provides \nadditional capabilities, however you can simply call in from your telephone using the number \nprovided above if your meeting will not include video or a presentation. Click the \"Help\" link for \nadditional information if you are a guest joining a Skype for Business meeting from your \ncomputer or mobile device for the first time. \nFor meeting organizers: Reset your dial-in PIN? \n+1 201-630-0824 \nflOC([CUSTOMINVITE])!] \nEFTA00009916",
    "pageCount": 2,
    "dataset": "Dataset 8"
  },
  "entities": {
    "people": [
      {
        "name": "Epstein Estate",
        "role": "extracted",
        "context": "Event: FW: Epstein Estate \nStart Date: 2020-11-09 21:30"
      },
      {
        "name": "Start Date",
        "role": "extracted",
        "context": "Event: FW: Epstein Estate \nStart Date: 2020-11-09 21:30:00 +0000 \nE"
      },
      {
        "name": "End Date",
        "role": "extracted",
        "context": "e: 2020-11-09 21:30:00 +0000 \nEnd Date: 2020-11-09 22:00:00 +0000 \nO"
      },
      {
        "name": "Skype Meeting",
        "role": "extracted",
        "context": "Weinstein, Marc A. \nLocation: Skype Meeting; Conference ID: 570 579 045;"
      },
      {
        "name": "Date Created",
        "role": "extracted",
        "context": "579 045; \nClass: X-PERSONAL \nDate Created: 2020-11-09 21:58:35 +0000 \nD"
      },
      {
        "name": "Date Modified",
        "role": "extracted",
        "context": "d: 2020-11-09 21:58:35 +0000 \nDate Modified: 2020-11-09 21:58:35 +0000 \nP"
      },
      {
        "name": "Original Appointment",
        "role": "extracted",
        "context": "9 15:30:14 +0000 \nAttendee: \n Original Appointment \nFrom: Weinstein, Marc A. \nSe"
      },
      {
        "name": "Andrew Tomback",
        "role": "extracted",
        "context": "5 AM \nTo: Weinstein, Marc A.; Andrew Tomback \nSubject: Epstein Estate \nWhe"
      },
      {
        "name": "Eastern Time",
        "role": "extracted",
        "context": "0 4:30 PM-5:00 PM (UTC-05:00) Eastern Time (US & Canada). \nWhere: Skype"
      },
      {
        "name": "In Information",
        "role": "extracted",
        "context": "erence ID: 570 579 045; \nDial-In Information (for meetings with no present"
      },
      {
        "name": "In Number",
        "role": "extracted",
        "context": "presentations or video) \nDial-In Number: \nConference ID: \nOne touch d"
      },
      {
        "name": "Additional Dial",
        "role": "extracted",
        "context": "nference ID: \nOne touch dial-\nAdditional Dial-\nBrazil \n+1 (201) 630-0824 \n5"
      },
      {
        "name": "In Numbers",
        "role": "extracted",
        "context": "phone (via cellular service) \nIn Numbers \n+55 11 3181-5692 \nCanada +1"
      },
      {
        "name": "United Kingdom",
        "role": "extracted",
        "context": "208 \nSingapore +65 3157 0147 \nUnited Kingdom +44 20 3443 6288 \nUnited Stat"
      },
      {
        "name": "Help \nTry",
        "role": "extracted",
        "context": "network/internet connection) \nHelp \nTry Skype Web App if you are havi"
      },
      {
        "name": "Skype Web",
        "role": "extracted",
        "context": "ternet connection) \nHelp \nTry Skype Web App if you are having trouble"
      }
    ],
    "locations": [],
    "dates": [
      {
        "date": "2020-11-09",
        "event": "2020-11-09"
      },
      {
        "date": "2020-11-09",
        "event": "November 9, 2020"
      }
    ],
    "flights": [],
    "phone_numbers": [
      "647-749-1240",
      "400 842 8305",
      "201-630-0824",
      "+1 647-749-1240",
      "+1 201-630-0824"
    ],
    "organizations": []
  },
  "processedAt": "2025-12-23T12:25:40.904Z"
}