{
  "document": {
    "id": "efta00030926",
    "filename": "EFTA00030926.pdf",
    "path": "C:\\Users\\user\\CascadeProjects\\epsteinexposed\\apps\\web\\DataSet 8\\VOL00008\\IMAGES\\0007\\EFTA00030926.pdf",
    "text": "\n\nFrom: ' \nTo:' \nSubject: RE: Discovery Requests \nDate: Wed, 03 Feb 2021 20:00:07 +0000 \nInline-Images: image001.jpg; image002.jpg \nr \ncI \nFor reference, the tracking numbers are \nFrom: \nSent: Wednesday, February 3, 2021 2:56 PM \nTo: \nSubject: RE: Discovery Requests \nGreat, thank you! \nFrom: \nSent: Wednesday, February 3, 2021 1:07 PM \nTo: \nSubject: RE: Discovery Requests \nand â€”  thanks! O \nHi \n! I've loaded the flash drive with the bates ranges defense counsel requested, and it will be ready to leave for \npickup momentarily. The password for the drive is \nI'm about to start loading a disc with the Ninth Production and re-stamped items for MDC now. I'll let you know when that \nhas been left for FedEx pickup this afternoon. Thank you! \nFrom: \nSent: Tuesday, February 2, 2021 8:54 AM \nTo: \nSubject: RE: Discovery Requests \nPerfect, thank you! \nFrom: \nSent: Tuesday, February 2, 2021 8:36 AM \nTo: \nSubject: RE: Discovery Requests \nGood morning! If it's okay with everyone, I will be in the Office tomorrow and can load this drive (and the disc for MDC \nwith the latest Ninth Production) then. Thanks very much! \nFrom: \nSent: Monday, February 1, 2021 2:34 PM \nTo: \nSubject: FW: Discovery Requests \nEFTA00030926\n\nFYI. I'm not going to be able to come into the office this week. Will someone be in and able to check the mail for this \ndrive and get it loaded? \nFrom: \nSent: Sunday, January 31, 2021 10:41 PM \nTo: \n) \n(USANYS)\nCc: \n>; \nSubject: RE: Discovery Requests \nHi \nWe will provide you with a drive to load the files. If our messenger service is functioning tomorrow (depending on the \nseverity of the snow storm) we will drop it off tomorrow. If not, we will drop it off Tuesday morning. \nThanks, \nFrom: rmailto \nSent: Frida Janua 29 2021 4:41 PM \nTo: \nSubject: RE: Discovery Requests \nOur paralegals reminded me that we have produced the ranges you included in your most recent email twice: once in the \nthird production (08-21-2020) and once in the reproduction with shortened file names (09-03-2020). We can certainly \nproduce them a third time, but we would not be able to reproduce them again through your FTP link, as they are too \nlarge. Please provide us with a 64 GB drive if you would like us to reproduce those ranges. \nBest, \nAssistant United States Attorney \nSouthern District of New York \n0007 \n212-637-2324 \nFrom: \nSent: Friday, January 29, 2021 4:08 PM \nTo: \n(USANYS) \nCc. \nSubject: RE: Discovery Requests \nEFTA00030927\n\nThank you for sending the link. I will ask our paralegals to use it to send you the ranges you requested, including the \nranges you referenced in your most recent email. \nBest, \nAssistant United States Attorney \nSouthern District of New York \nFrom: \nSent: Friday, January 29, 2021 3:53 PM \nTo: \n< \n(usANys) c> \nCc: \n>; \nSubject: RE: Discovery Requests \nThanks for the follow-up. Please send the documents to the FTP link below: \nAlso, we are missing the Bates ranges listed below. \nSDNY_GM_00167911 through SDNY_GM_00168477 \nSDNY_GM_00168488 through SDNY_GM_00169165 \nSDNY_GM_00169184 through SDNY_GM_00169491 \nSDNY_GM_00169505 through SDNY_GM_00169735 \nWe had discussed these ranges several months ago and I believe you had agreed to reproduce them in the 11/9 \nproduction. But we do not appear to have received them. Can you send these ranges via the FTP site as well? \nThanks, \nFrom: \n) \n[mailto \nSent: Fnda Janua 29 2021 10:31 AM \nTo: \nSubject: RE: Discovery Requests \nEFTA00030928\n\nFollowing up on this, we have now prepared all of the items you requested in point 6 below for production to you. Our \nparalegals have sent a copy of the materials to the MDC for your client. Would you like to provide us with an FTP link for \nthis production, or would you like us to prepare a CD for you instead? \nThanks, \nAssistant United States Attorney \nSouthern District of New York \nFrom: \nSent: Monday, January 25, 2021 3:56 PM \nTo: \n; < \n(USANYS)\nCc: \nSubject: RE: Discovery Requests \nFollowing up on point 6 below, our paralegals have re-stamped the materials you identified with a Bates range overlap \nand are prepared to reproduce those materials to you. The materials are small enough to produce via your FTP site. \nWould you like to send us a link to where you would like those materials uploaded? Alternatively, we can load the \nmaterials to a CD and send it to you. \nWe are still waiting to hear back from our vendor about the remaining issues you identified in point 6. \nThanks, \nAssistant United States Attorney \nSouthern District of New York \nFrom: \nSent: Sunday, January 17, 2021 10:05 PM \nTo: \nEFTA00030929\n\n(USANYS) \nCc: \nSubject: RE: Discovery Requests \nBelow please find our responses. \n1. As we have recently discussed, Ms. Maxwell now has access to the 4TB drive containing a full set of the discovery \nproduced to date. It took a significant amount of time to create this copy due to the volume of discovery and \ndelays on the part of our vendor, who assisted in creating the copy. \n2. As we have recently discussed, Ms. Maxwell now has a drive containing the contents of the CD produced on \nNovember 18, 2020. \n3. As I conveyed to you over the phone and in a recent email, the materials produced from the Subject Devices all \ncontain metadata indicating the \"NYC\" CART Evidence Number of the device from which each document was \nextracted. In our November 18, 2020 discovery letter, we provided you with a chart setting forth which \"NYC\" \nCART Evidence Number corresponds with which Subject Device in our warrants. If you still need a detailed index \nof all 1.2 million documents with the specific Subject Device indicated, please let me know, and I will ask one of \nour paralegals to compile one. \n4. We produced the FBI report bearing Bates number SDNY_GM_02050812-14 in the form in which it was \nrecovered from one of Epstein's devices. In other words, we did not apply any redactions to that document; \nrather, the redactions existed on the document at the time the document was found during the FBI's search of \nEpstein's devices. We are not aware of any legal basis for your request for a log of redactions. If you have any \nlegal authority on that point, we would be happy to consider it. As a  courtesy, I will note that our office did not \napply redactions to any material that was identified responsive during the searches of Epstein's devices. \n5. We are aware of our discovery obligations, have complied with them, and will continue to comply with them. We \nare not aware of any legal basis for your request that we inform you of what, if any, documents have been \nwithheld or the basis for their withholding. If you have any legal authority on that point, we would be happy to \nconsider it. As a courtesy, I will note that we have provided you with all records we received from and all \nrecords we received from .  As to your inquiry about the Bates ranges on the documents \nbeginning with Bates number \"28', I note that the folder containing the subpoena returns in our August \n5, 2020 production included two documents. The first (SDNY_GM_00005532-5649) is the document you \nreferenced in your email inquiry. The second (SDNY_GM_00005650-5676) is 27 pages long, accounting for the \nfirst 27 pages of the production from .  We produced those two documents in the form in which we \nreceived them. \n6. Our paralegals are working on the issues you identified with Bates ranges and metadata load files. I will reach \nback out to you once I have an update on the status of those issues. \n7. We do not have a more detailed index of the November 9 and November 18 productions beyond what we have \nprovided to you. \n8. We are not aware of any legal basis for your request for copies of grand jury subpoenas. Nor are we aware of any \nlegal basis for your request that we identify the date range of documents we requested in each subpoena. If you \nhave any legal authority for those requests, we would be happy to consider it. \n9. The court filings that appear to be referenced in the Daily Beast article you sent are an application for a search \nwarrant and a search warrant filed in the District of New Hampshire. We produced both documents to you in \ndiscovery on August 5, 2020. The DNH judge issued a sealing order in connection with the warrant and \nEFTA00030930\n\napplication. As you can see at Bates No. SDNY_GM_00000621, the sealing order automatically expired on \nDecember 30, 2020. Our understanding is that the District of New Hampshire unsealed the filing of its own \naccord in conformity with the clear language of that sealing order. Our office took no affirmative steps to unseal \nor otherwise release these filings. \nBest, \nAssistant United States Attorney \nSouthern District of New York \nFrom: \nSent: Thursday, January 7, 20214:13 PM \nTo: \n(USANYS) \nCc: \n< \nSubject: Discovery Requests \n>; \nWe write to raise a number of discovery issues. Please let us know your position on these issues at your earliest \nconvenience. \n1. In our email correspondence on 11/18/2020, you agreed to create a new hard drive containing the entire discovery \nproduction. We provided you with a 4TB hard drive for that purpose on 11/20/2020. It is very important for Ms. \nMaxwell to have this drive as soon as possible to prepare her defense. Do you have an update on when the drive \nwill be ready? \n2. We also informed you that the CD produced on November 18, 2020 did not work on the prison computer at the \nMDC (as you know, the laptop provided to Ms. Maxwell does not have a CD drive). Accordingly, we asked you to \ninclude the material on the CD in the new 4TB hard drive. We followed-up with you about this issue on December \n30, 2020. Given that the new hard drive is still not ready, we ask that you download the material on the CD onto \na separate thumb drive or hard drive and provide it as quickly as possible to Ms. Maxwell at the MDC so that she \ncan review the materials this weekend. Alternatively, you can provide an external CD drive to Ms. Maxwell at \nthe MDC so that she can read the files on the MDC computer. We will provide whatever media device you \nrequire to facilitate this production. \n3. Unlike the November 9, 2020 discovery cover letter, the November 18, 2020 discovery cover letter (attached) does \nnot correlate the Bates numbers to the particular \"Subject Device\" from which the documents were recovered. \nInstead, the cover letter indicates that the documents came from \"SDNY_PROD015\" or \"SDNY_PROD0167 We do \nnot know what those terms refer to. We request that the government produce a list that correlates the Bates \nnumbers for all of the documents in SDNY_PROD015 and SDNY_PROD016 to the particular devices from which the \ndocuments were recovered. \n4. We request that the government provide an unredacted version of the FBI report, dated December 6, 2006, \nbearing Bates number SDNY_GM_02050812-14 (attached). We also request that the government produce a  log \nEFTA00030931\n\nidentifying all of the redacted documents in the discovery and the bases for each of the redactions. \n5. There are a few documents that seem to be missing from the discovery. For example, the documents \n(SDNY_GM_00001015-3637) do not seem to include subscriber information for the various phone numbers. Also, \nthe flight logs produced by begin at Bates number suggesting that \nwere not produced to us. Please produce these documents to us or provide an \nexplanation why you are not producing them to us. Please confirm whether there are other documents that were \nremoved from the grand jury subpoena productions that we have not yet identified and the basis for their removal. \n6. There are a few Bates number/metadata issues with some of the documents: \na. There is an overlap between the fourth and fifth document productions. The fourth production ends at \nSDNY_GM_00328863, the fifth production begins at SDNY_GM_00328070. We propose renumbering the \nrange from the fifth production (i.e., renumber SDNY_GM_00328070-328863). \nb. The metadata load files (*.DAT) for PROD011 had a number of gaps which are detailed in the attached Excel \nfile. We propose that you send us a  new DAT file covering only the missing documents. \nc. The metadata load files (*.DAT) for PROD015 had a gap from SDNY_GM_00723971 to SDNY_GM_00723981. \nWe propose that you send us a new DAT file covering only the missing documents. \n7. To the extent that the government has created an index of the documents produced on November 9 and \nNovember 18 that is more detailed than the production cover letters, we request that you provide a copy to the \ndefense. \n8. We request that the government provide copies of the grand jury subpoenas for documents issued by the \ngovernment in this case. Also, please identify the date range of documents you requested in each subpoena. \nThere is one other issue we'd like to raise. An article in the Daily Beast on Monday referenced the search warrant affidavit \nfor the cell-site simulator used to track Ms. Maxwell's cellphone before her arrest (https://www.thedailybeast.com/how-\nthe-fbi-tracked-down-ghislaine-maxwell-alleged-madam-of-jeffrey-epstein).  The article stated that the affidavit appeared \nin a  \"newly unsealed court filing.\" I don't recall this affidavit being unsealed or referenced in anything that was filed on \nthe court docket. Please confirm whether or not the government unsealed this affidavit or any other materials from the \ncriminal discovery, and whether any discovery materials were released pursuant to FOIA requests. \nRegards, \nCOHEN & GRESSER LLP \nEltin I  view bio \nwww.cohengresser.com \nNew York I  Paris I  Washington DC I  London \nEFTA00030932\n\nCONFIDENTIALITY NOTICE: The information contained in this e-mail may be confidential and/or privileged. This e-mail is intended to be reviewed initially by only \nthe individual named above. If the reader of this e-mail is not the intended recipient or a representative of the intended recipient. you are hereby notified that any \nreview. dissemination or copying of this e-mail or the information contained herein is prohibited. If you have received this e-mail in error. please immediately notify \nthe sender by telephone and permanently delete this e-mail. Thank you. \nPRIVACY: A complete copy of our privacy policy can be viewed a! SInikerew.cohenpressercom/privacK-policx\nEFTA00030933",
    "pageCount": 8,
    "dataset": "Dataset 8"
  },
  "entities": {
    "people": [
      {
        "name": "Maxwell",
        "role": "extracted",
        "context": "s we have recently discussed, Ms. Maxwell now has access to the 4TB"
      },
      {
        "name": "Discovery Requests",
        "role": "extracted",
        "context": "From: ' \nTo:' \nSubject: RE: Discovery Requests \nDate: Wed, 03 Feb 2021 20:00"
      },
      {
        "name": "Ninth Production",
        "role": "extracted",
        "context": "start loading a disc with the Ninth Production and re-stamped items for MDC"
      },
      {
        "name": "Hi \nWe",
        "role": "extracted",
        "context": "ject: RE: Discovery Requests \nHi \nWe will provide you with a drive"
      },
      {
        "name": "Frida Janua",
        "role": "extracted",
        "context": "Thanks, \nFrom: rmailto \nSent: Frida Janua 29 2021 4:41 PM \nTo: \nSubject"
      },
      {
        "name": "Assistant United",
        "role": "extracted",
        "context": "produce those ranges. \nBest, \nAssistant United States Attorney \nSouthern Dis"
      },
      {
        "name": "States Attorney",
        "role": "extracted",
        "context": "ges. \nBest, \nAssistant United States Attorney \nSouthern District of New Yor"
      },
      {
        "name": "Southern District",
        "role": "extracted",
        "context": "stant United States Attorney \nSouthern District of New York \n0007 \n212-637-23"
      },
      {
        "name": "Fnda Janua",
        "role": "extracted",
        "context": "ks, \nFrom: \n) \n[mailto \nSent: Fnda Janua 29 2021 10:31 AM \nTo: \nSubjec"
      },
      {
        "name": "Subject Devices",
        "role": "extracted",
        "context": "e materials produced from the Subject Devices all \ncontain metadata indicat"
      },
      {
        "name": "Evidence Number",
        "role": "extracted",
        "context": "ata indicating the \"NYC\" CART Evidence Number of the device from which each"
      },
      {
        "name": "Subject Device",
        "role": "extracted",
        "context": "Number corresponds with which Subject Device in our warrants. If you still"
      },
      {
        "name": "Daily Beast",
        "role": "extracted",
        "context": "ppear to be referenced in the Daily Beast article you sent are an appli"
      },
      {
        "name": "New Hampshire",
        "role": "extracted",
        "context": "rant filed in the District of New Hampshire. We produced both documents t"
      },
      {
        "name": "Bates No",
        "role": "extracted",
        "context": "pplication. As you can see at Bates No. SDNY_GM_00000621, the sealin"
      }
    ],
    "locations": [],
    "dates": [
      {
        "date": "2020-08-21",
        "event": "08-21-2020"
      },
      {
        "date": "2020-09-03",
        "event": "09-03-2020"
      },
      {
        "date": "2020-11-18",
        "event": "11/18/2020"
      },
      {
        "date": "2020-11-20",
        "event": "11/20/2020"
      },
      {
        "date": "2021-02-03",
        "event": "February 3, 2021"
      },
      {
        "date": "2021-02-02",
        "event": "February 2, 2021"
      },
      {
        "date": "2021-02-01",
        "event": "February 1, 2021"
      },
      {
        "date": "2021-01-31",
        "event": "January 31, 2021"
      },
      {
        "date": "2021-01-29",
        "event": "January 29, 2021"
      },
      {
        "date": "2021-01-25",
        "event": "January 25, 2021"
      },
      {
        "date": "2021-01-17",
        "event": "January 17, 2021"
      },
      {
        "date": "2020-11-18",
        "event": "November 18, 2020"
      },
      {
        "date": "2020-08-05",
        "event": "August \n5, 2020"
      },
      {
        "date": "2020-08-05",
        "event": "August 5, 2020"
      },
      {
        "date": "2020-12-30",
        "event": "December 30, 2020"
      },
      {
        "date": "2020-12-30",
        "event": "December \n30, 2020"
      },
      {
        "date": "2020-11-09",
        "event": "November 9, 2020"
      },
      {
        "date": "2006-12-06",
        "event": "December 6, 2006"
      }
    ],
    "flights": [],
    "phone_numbers": [
      "212-637-2324"
    ],
    "organizations": []
  },
  "processedAt": "2025-12-23T12:26:27.046Z"
}