{
  "document": {
    "id": "efta00020956",
    "filename": "EFTA00020956.pdf",
    "path": "C:\\Users\\user\\CascadeProjects\\epsteinexposed\\apps\\web\\DataSet 8\\VOL00008\\IMAGES\\0004\\EFTA00020956.pdf",
    "text": "\n\nFrom: \"cmecf®ca2.uscourts.gov\" \n<cmecf®ca2.uscourts.gov> \nTo: -4 \nSubject: 19-2221 United States of America v. Epstein \"Notice of Appearance for Additional or Substitute \nCounsel FILED\" \nDate: Mon, 05 Aug 2019 22:38:38 +0000 \n***NOTE TO PUBLIC ACCESS USERS*** Judicial Conference of the United States policy permits \nattorneys of record and parties in a case (including pro se litigants) to receive one free electronic copy of \nall documents filed electronically, if receipt is required by law or directed by the filer. PACER access fees \napply to all other users. To avoid later charges, download a copy of each document during this first \nviewing. \nCourt of Appeals, 2nd Circuit \nNotice of Docket Activity \nThe following transaction was filed on 08/05/2019 \nCase Name: United States of America v. Epstein \nCase Number: 19-2221 \nDocument(s): Document(s)\nDocket Text: \nNOTICE OF APPEARANCE AS ADDITIONAL COUNSEL, on behalf of Appellee USA United States of \nAmerica, FILED. Service date 08/05/2019 by CMIECF. [2624675] [19-2221] \nNotice will be electronically mailed to: \nMartin G. Weinbe owlmc att.net owlm w att.net \nMs. \n, Assistant U.S. Attome \nReid Weingarten, -: , ehartman@steptoe.com, \nocorn@steptoe.com \nDonnell G. Bolden, Deputy Clerk: Donnell Bolden a ca2.uscourts. ov \nAssistant U.S. Attorney: \nNotice will be stored in the notice cart for: \nDonnell G. Bolden, Deputy Clerk \nQuality Control 1 \nThe following document(s) are associated with this transaction: \nDocument Description: Notice of Appearance for Additional or Substitute Counsel FILED \nOriginal Filename: 2019-08-05, appeal, DeFilippo, notice of appearance (for filing).pdf \nElectronic Document Stamp: \n[STAMP acecfStampil: 1161632333 [Date—08/05/2019] [FileNumber=2624675-0] \n[36f79752f9558aa0b34c903bb005723e3d85bda5b78e0f67382ce190f3a8438353c63954883b59c0da213080182c \nEFTA00020956\n\n550525efSee5037dOadf8311e9fc31185321]] \nEFTA00020957",
    "pageCount": 2,
    "dataset": "Dataset 8"
  },
  "entities": {
    "people": [
      {
        "name": "Substitute \nCounsel",
        "role": "extracted",
        "context": "Appearance for Additional or Substitute \nCounsel FILED\" \nDate: Mon, 05 Aug 201"
      },
      {
        "name": "Judicial Conference",
        "role": "extracted",
        "context": "OTE TO PUBLIC ACCESS USERS*** Judicial Conference of the United States policy p"
      },
      {
        "name": "Circuit \nNotice",
        "role": "extracted",
        "context": "ewing. \nCourt of Appeals, 2nd Circuit \nNotice of Docket Activity \nThe follo"
      },
      {
        "name": "Docket Activity",
        "role": "extracted",
        "context": "peals, 2nd Circuit \nNotice of Docket Activity \nThe following transaction wa"
      },
      {
        "name": "Case Name",
        "role": "extracted",
        "context": "tion was filed on 08/05/2019 \nCase Name: United States of America v."
      },
      {
        "name": "Epstein \nCase",
        "role": "extracted",
        "context": ": United States of America v. Epstein \nCase Number: 19-2221 \nDocument(s):"
      },
      {
        "name": "Docket Text",
        "role": "extracted",
        "context": "221 \nDocument(s): Document(s)\nDocket Text: \nNOTICE OF APPEARANCE AS ADD"
      },
      {
        "name": "Attome \nReid",
        "role": "extracted",
        "context": "tt.net \nMs. \n, Assistant U.S. Attome \nReid Weingarten, -: , ehartman@ste"
      },
      {
        "name": "Deputy Clerk",
        "role": "extracted",
        "context": "eptoe.com \nDonnell G. Bolden, Deputy Clerk: Donnell Bolden a ca2.uscourt"
      },
      {
        "name": "Donnell Bolden",
        "role": "extracted",
        "context": "nell G. Bolden, Deputy Clerk: Donnell Bolden a ca2.uscourts. ov \nAssistant"
      },
      {
        "name": "Quality Control",
        "role": "extracted",
        "context": "nell G. Bolden, Deputy Clerk \nQuality Control 1 \nThe following document(s)"
      },
      {
        "name": "Document Description",
        "role": "extracted",
        "context": "iated with this transaction: \nDocument Description: Notice of Appearance for Add"
      },
      {
        "name": "Substitute Counsel",
        "role": "extracted",
        "context": "Appearance for Additional or Substitute Counsel FILED \nOriginal Filename: 201"
      },
      {
        "name": "Original Filename",
        "role": "extracted",
        "context": "or Substitute Counsel FILED \nOriginal Filename: 2019-08-05, appeal, DeFilipp"
      },
      {
        "name": "Electronic Document",
        "role": "extracted",
        "context": "appearance (for filing).pdf \nElectronic Document Stamp: \n[STAMP acecfStampil:"
      }
    ],
    "locations": [],
    "dates": [
      {
        "date": "2019-08-05",
        "event": "08/05/2019"
      },
      {
        "date": "2019-08-05",
        "event": "2019-08-05"
      }
    ],
    "flights": [],
    "phone_numbers": [
      "1161632333"
    ],
    "organizations": []
  },
  "processedAt": "2025-12-23T12:26:03.701Z"
}