{
  "document": {
    "id": "efta00021879",
    "filename": "EFTA00021879.pdf",
    "path": "C:\\Users\\user\\CascadeProjects\\epsteinexposed\\apps\\web\\DataSet 8\\VOL00008\\IMAGES\\0004\\EFTA00021879.pdf",
    "text": "\n\nFrom: Sigrid McCawley <smccawley@bsfllp.com> \nTo: \nSubject: Filing \nDate: Mon, 10 Aug 2020 23:57:54 +0000 \nAttachments: 2020-08-10 J01100-00OLLETTEtaddressettojudge_Loretta_A.freskafrom_....pdf; \n2020-08-10 J01100-001LExhibit_A.PDF \nAre you able to shed light on what Menninger is trying to intimate in this first paragraph? I just want to prepare if there is \nsomething I need to know about. This letter comes as part of the unsealing process. \nBest, \nSigrid \nSigrid McCawley \nPartner \nBOIES SCHILLER FLEXNER LLP \n401 E. Las Olas Blvd. Suite 1200 \nFort Lauderdale, FL, 33301 \n(t) +1 954 377 4223 \n(m)+1 954 770 5377 \nsmccawley@bsfllp.com \nwww.bsfllp.com\nThe information contained in this electronic message is confidential information intended only for the use of the named recipient(s) and may contain information that. \namong other protections, is the subject of attomey-client privilege. attorney work product or exempt from disclosure under applicable law. If the reader of this \nelectronic message is not the named recipient, or the employee or agent responsible to deliver it to the named recipient. you are hereby notified that any \ndissemination. distribution. copying or other use of this communication is strictly prohibited and no privilege is waived. If you have received this communication in \nerror. please immediately notify the sender by replying to this electronic message and then deleting this electronic message from your computer. (v.1 08201831BS9 \nEFTA00021879",
    "pageCount": 1,
    "dataset": "Dataset 8"
  },
  "entities": {
    "people": [
      {
        "name": "Sigrid Mc",
        "role": "extracted",
        "context": "From: Sigrid McCawley <smccawley@bsfllp.com>"
      },
      {
        "name": "Filing \nDate",
        "role": "extracted",
        "context": "ey@bsfllp.com> \nTo: \nSubject: Filing \nDate: Mon, 10 Aug 2020 23:57:54 +0"
      },
      {
        "name": "Sigrid \nSigrid",
        "role": "extracted",
        "context": "he unsealing process. \nBest, \nSigrid \nSigrid McCawley \nPartner \nBOIES SCHI"
      },
      {
        "name": "Cawley \nPartner",
        "role": "extracted",
        "context": "ess. \nBest, \nSigrid \nSigrid McCawley \nPartner \nBOIES SCHILLER FLEXNER LLP"
      },
      {
        "name": "Las Olas",
        "role": "extracted",
        "context": "SCHILLER FLEXNER LLP \n401 E. Las Olas Blvd. Suite 1200 \nFort Lauder"
      },
      {
        "name": "Fort Lauderdale",
        "role": "extracted",
        "context": "E. Las Olas Blvd. Suite 1200 \nFort Lauderdale, FL, 33301 \n(t) +1 954 377 42"
      }
    ],
    "locations": [
      {
        "name": "Fort Lauderdale, FL",
        "type": "city"
      }
    ],
    "dates": [
      {
        "date": "2020-08-10",
        "event": "2020-08-10"
      }
    ],
    "flights": [],
    "phone_numbers": [
      "954 377 4223",
      "954 770 5377",
      "+1 954 377 4223",
      "+1 954 770 5377"
    ],
    "organizations": []
  },
  "processedAt": "2025-12-23T12:26:05.612Z"
}